{
    "Contributors": [
        "Jacob Anderson"
    ],
    "Source": [
        "paws-x",
        "https://huggingface.co/datasets/paws-x"
    ],
    "Categories": [
        "Translation"
    ],
    "Input_language": [
        "Chinese"
    ],
    "Output_language": [
        "English"
    ],
    "Definition": "Given a sentence in Chinese, provide an equivalent paraphrased translation in English that retains the same meaning both through the translation and the paraphrase.",
    "Positive Examples": [
        {
            "input": "1975年的NBA赛季 -  76赛季是全美篮球协会的第30个赛季。",
            "output": "The 1975 -- 76 season of the National Basketball Association was the 30th season of the NBA .",
            "explanation": "This is a correct and accurate translation from Chinese to English because the translated paraphrase retains the main message that between the years 1975-1976, the 30th NBA season occurred."
        },
        {
            "input": "当可以保持相当的流速时，结果很高。",
            "output": "The results are high when comparable flow rates can be maintained .",
            "explanation": "The resulting paraphrased translation from Chinese to English is correct because the resulting translation holds the message that results are high when comparable rates of flow are maintained."
        }
    ],
    "Negative Examples": [
        {
            "input": "1560年10月，他在巴黎秘密会见了英国大使Nicolas Throckmorton，要求他通过苏格兰返回英国。",
            "output": "In October 1560 , he secretly met with the English ambassador , Nicolas Throckmorton , in Paris , and asked him for a passport to return to Scotland through England .",
            "explanation": "This is not a proper translation from Chinese to English because the resulting translation is not accurate to the original idea in which the locations of England and Scotland are not accurate."
        },
        {
            "input": "还有具体的讨论，公众形象辩论和项目讨论。",
            "output": "There are also public discussions , profile specific discussions , and project discussions .",
            "explanation": "This translated paraphrase from Chinese to English is incorrect because the resulting translation does not reflect the actual topics of dicussion and debate relating to profiles and projects."
        }
    ],
    "Instances": [
        {
            "input": "他是形而上学文学，神学和古典科学的学者。",
            "output": [
                "He was a scholar in metaphysical literature , theology , and classical science ."
            ]
        },
        {
            "input": "这座城市坐落在蛇河（Snake River）与伟大的威瑟河（Weiser River）的交汇处，这条河与俄勒冈州（Oregon）接壤。",
            "output": [
                "The city lies at the confluence of the Snake River and the Great Weiser River , which marks the border with Oregon ."
            ]
        },
        {
            "input": "云达的部队投资了贝尔福，并于11月3日抵达该市。",
            "output": [
                "Werder 's troops invested Belfort and reached the city on November 3 ."
            ]
        },
        {
            "input": "前十五件武器是在1916年上半年交付的，在战争结束时共完成了57桶和56辆汽车。",
            "output": [
                "The first five weapons were delivered in the first half of 1916 . A total of 57 barrels and 56 carriages were completed by the end of the war ."
            ]
        },
        {
            "input": "他和邓肯之间的友谊在1951年的一次俱乐部会议上结束，当时两人在一次年会上不同意，邓肯报告说，格里夫斯说：",
            "output": [
                "The friendship between him and Duncan ended in 1951 at a club meeting , when the two did not agree at an annual meeting , and Duncan reported that Greaves said :"
            ]
        },
        {
            "input": "Shaffer Creek是美国宾夕法尼亚州贝德福德郡Raystown Branch Juniata River（Brush Creek）的支流。",
            "output": [
                "Shaffer Creek is an tributary of Brush Creek ( Raystown Branch Juniata River ) in Bedford County , Pennsylvania in the United States ."
            ]
        },
        {
            "input": "布里格斯后来在1967年的蒙特利流行音乐节上遇见了布里格斯，拉维·尚卡尔也在那里与埃里克·伯登和动物一起表演。",
            "output": [
                "Briggs met Briggs later at the Monterey Pop Festival of 1967 , where Ravi Shankar also performed with Eric Burdon and The Animals ."
            ]
        },
        {
            "input": "女主角扮演的角色是科尔特斯在“阿里巴巴和神圣的王冠”中扮演的角色，由Erminio Salvi执导。",
            "output": [
                "Cortez played the female lead in \" Ali Baba and the Sacred Crown \" , directed by Erminio Salvi ."
            ]
        },
        {
            "input": "她曾在斯图加特，柏林（德国）和维也纳（奥地利）工作和生活。",
            "output": [
                "She worked and lived in Germany ( Stuttgart , Berlin ) and in Vienna ( Austria ) ."
            ]
        },
        {
            "input": "Aksuat Dendropark（俄语：Akshout Dendroparks）是一个天然纪念物（乌里扬诺夫斯克州保护区）",
            "output": [
                "Akshuat dendropark ( Russian : Акшуатский дендропарк ) is a natural monument ( Protected areas of Ulyanovsk Oblast )"
            ]
        },
        {
            "input": "Little Jocko河流经圣劳伦斯河和渥太华河到Jocko河。",
            "output": [
                "The Little Jocko River flows via the Saint Lawrence River and the Ottawa River to the Jocko River ."
            ]
        },
        {
            "input": "1951年，他于1956年去世并退休。",
            "output": [
                "He died in 1951 and retired in 1956 ."
            ]
        },
        {
            "input": "WORHP，也称为eNLP（欧洲NLP解算器），是一个数学软件库，用于在数值上大规模地解决连续的非线性优化问题。",
            "output": [
                "WORHP , also referred to as eNLP ( European NLP solver ) by ESA , is a mathematical software library for solving continuous large scale nonlinear optimization problems numerically ."
            ]
        },
        {
            "input": "叶子通常长1.5-4mm，宽0.2-0.7mm。",
            "output": [
                "The leaves are usually 1.5-4 mm long and 0.2-0.7 mm wide ."
            ]
        },
        {
            "input": "这些地理位置对应于传统的格拉斯哥区，南部，爱丁堡区以及北部和中部地区。",
            "output": [
                "These geographically roughly correspond to the traditional districts of Glasgow District , South , Edinburgh District and North and Midlands ."
            ]
        },
        {
            "input": "Quintus的梅特路斯是古罗马政治家和一般的卢修斯梅特路斯冠的第二个儿子。",
            "output": [
                "Quintus Caecilius Metellus Macedonicus was the second son of the Roman politician , General Lucius Caecilius Metellus Diadematus ."
            ]
        },
        {
            "input": "在这里，我们将伪差分算子视为微分算子的推广。",
            "output": [
                "We consider pseudo-differential operators here as a generalization of differential operators ."
            ]
        },
        {
            "input": "基于巴尔的摩市，仅提及，从未参观过的节目。",
            "output": [
                "Based on the city of Baltimore , only mentioned , has never visited in the show ."
            ]
        },
        {
            "input": "黛比唐纳是一个虚构的“周六夜现场”角色的名字，该角色于2004年首次亮相，由雷切尔·德拉奇描绘。",
            "output": [
                "Debbie Downer is a name of a fictional \" Saturday Night Live \" character who debuted in 2004 , and who was portrayed by Rachel Dratch ."
            ]
        },
        {
            "input": "Taieri是1866年至1911年在新西兰奥塔哥地区的前议会选民。",
            "output": [
                "Taieri is a former parliamentary electorate in the New Zealand region of Otago , from 1866 to 1911 ."
            ]
        },
        {
            "input": "布罗克顿位于罗德岛普罗维登斯东北约25英里处，距离波士顿以南30英里。",
            "output": [
                "Brockton is located approximately 25 miles northeast of Providence , Rhode Island and 30 miles south of Boston ."
            ]
        },
        {
            "input": "Seb Janiak是法国摄影师和波兰血统的视频总监。",
            "output": [
                "Seb Janiak is the French photographer and video director of Polish origin ."
            ]
        },
        {
            "input": "阿什利于1986年11月1日出生，是一位来自洛杉矶的当代舞者，最初在亚利桑那州长大。",
            "output": [
                "Born on November 1 , 1986 , Ashley is a contemporary dancer from Los Angeles who was originally raised in Arizona ."
            ]
        },
        {
            "input": "Dorothy Kate Richmond，Frances Hodgkins和Gwen Knight是斯图尔特的同代人。",
            "output": [
                "Dorothy Kate Richmond , Frances Hodgkins and Gwen Knight was a Stewart contemporary ."
            ]
        },
        {
            "input": "Hastings Ndlovu在约翰内斯堡的Avalon公墓与Hector Pieterson一起被埋葬。",
            "output": [
                "Hastings Ndlovu , together with Hector Pieterson , was buried at the Avalon cemetery in Johannesburg ."
            ]
        },
        {
            "input": "其他生产自杀车型的汽车制造商包括Citroën，Lancia，Opel，Panhard，Rover，Saab，Saturn，Skoda和Volkswagen。",
            "output": [
                "Other car manufacturers which have produced models with suicide doors include Opel , Lancia , Citroën , Panhard , Rover , Saab , Saturn , Škoda , and Volkswagen ."
            ]
        },
        {
            "input": "它覆盖着肥沃的红土基地的草原天然植被，以及肥沃土壤上的Saltbush丛林。",
            "output": [
                "It is covered with a natural vegetation of grassland of less fertile red clay soils , and saltbush shrubland on more fertile earths ."
            ]
        },
        {
            "input": "JontéBuhl（1982年4月4日出生）是一名前加拿大职业足球运动员，曾在加拿大足球联盟的埃德蒙顿爱斯基摩人队效力四年。",
            "output": [
                "Jonté Buhl ( born April 4 , 1982 ) is a Canadian former professional football cornerback who played four seasons for the Edmonton Eskimos of the Canadian Football League ."
            ]
        },
        {
            "input": "她效力于奥兰联队的女子联盟。",
            "output": [
                "She plays for Naisten Liiga of the Åland United ."
            ]
        },
        {
            "input": "较小的小交叉电路挂架可以在一侧具有两个单臂而在另一侧具有一个。",
            "output": [
                "Smaller small cross pylons may have two single arms on one side and one on the other ."
            ]
        },
        {
            "input": "“The Timber”于2015年2月27日在北美发布，Well Go USA Entertainment于2015年10月6日在德国发布。",
            "output": [
                "On February 27 , 2015 , \" The Timber \" was released in North America , Well Go USA Entertainment was released on October 6 , 2015 in Germany ."
            ]
        },
        {
            "input": "尽管印刷了该系列的五期，但该项目完成后没有任何一项被中止。",
            "output": [
                "Although five issues of the series were printed , the project was finished without any of them being cancelled ."
            ]
        },
        {
            "input": "作为一名作曲家，Lars Ankerstjerne为Nik＆Jay，Burhan G和Rasmus Seebach创作了歌曲。",
            "output": [
                "Lars Ankerstjerne has written as songwriter for Nik 'Jay , Burhan G and Rasmus Seebach songs ."
            ]
        },
        {
            "input": "2011年7月7日，Russell在哥伦布蓝夹克上交易Kris Russell，并与Blue Jackets组织的兄弟Michael Blunden一起参加。",
            "output": [
                "On July 7 , 2011 , Russell was traded to the Columbus Blue Jackets for Kris Russell . He joined his brother Michael Blunden with the Blue Jackets organization ."
            ]
        },
        {
            "input": "（Don Wyatt曾在1956年一直在企鹅中，而Eddie和Ray在后来的Colts / Fortunes中都与Ray在一起。）",
            "output": [
                "( Don Wyatt had been in the Penguins in 1956 and both Eddie and Ray had been in the later Colts/Fortunes with Ray . )"
            ]
        },
        {
            "input": "相比之下，旅鼠显着地着色并且对掠食者甚至人类观察者表现得很积极。",
            "output": [
                "By contrast , the lemmings are strikingly colored and behave aggressively towards predators and even human observers ."
            ]
        },
        {
            "input": "它位于Shawnee镇，毗邻艾伦县的Duchouquet镇。",
            "output": [
                "It is located in Shawnee Township and is adjacent to Duchouquet Township in Allen County ."
            ]
        },
        {
            "input": "2007-08赛季堪萨斯州野猫队男子篮球队代表堪萨斯州立大学参加2007-08赛季的大学篮球赛季。",
            "output": [
                "The 2007 -- 08 Kansas State Wildcats men 's basketball team represented Kansas State University in the 2007 -- 08 college basketball season ."
            ]
        },
        {
            "input": "这是本赛季结束的最后一场AFL锦标赛; 1966赛季之后的第一个超级碗。",
            "output": [
                "This was the last AFL Championship to complete the season , the first Super Bowl followed in the 1966 season ."
            ]
        },
        {
            "input": "解雇后，他从德国搬到新墨西哥州，然后到洛杉矶，然后到旧金山。",
            "output": [
                "After his discharge he moved from Germany to New Mexico and then to Los Angeles then to San Francisco ."
            ]
        },
        {
            "input": "Zrinski和Frankopan的骨头于1907年在奥地利被发现并于1919年被带到萨格勒布，在那里他们在萨格勒布大教堂重新安葬。",
            "output": [
                "The bones of Zrinski and Frankopan were found in 1907 in Austria and brought to Zagreb in 1919 , where they were rebuilt in the Zagreb Cathedral ."
            ]
        },
        {
            "input": "下面是专辑的早期版本，其中包含所有原始片段和“胜利者的牺牲”，在早期配置中略长。",
            "output": [
                "Below is the early version of the album with all the original segues . Also , \" The Sacrifice of Victor \" is slightly longer on the early configuration ."
            ]
        },
        {
            "input": "还创造了几个电子动画角色......一只巨大的鹅（Galaga）和一个用于木偶的Cernos的电子动画头。",
            "output": [
                "There were also several animatronic characters created ... a giant goose ( Galaga ) and an animatronic head for the doll 's cernos ."
            ]
        },
        {
            "input": "特拉布宗世界贸易中心的大楼靠近特拉布宗机场。",
            "output": [
                "The complex of World Trade Center Trabzon is situated close to Trabzon Airport ."
            ]
        },
        {
            "input": "Laetitia Pujol像Man一样阴暗的存在; Karl Paquette是他强壮，忧郁的双重身份;和Mathieu Ganio描绘了女人。",
            "output": [
                "Laetitia Pujol was a shady presence as Le Homme , Karl Paquette was his strong , melancholy double , and Mathieu Ganio portrayed La Femme ."
            ]
        },
        {
            "input": "克里斯伊根（尼克史密斯）与他的家人在夏日湾安顿下来，他和邓肯很快成为朋友并陷入各种危机。",
            "output": [
                "Nick Smith ( Chris Egan ) settles in Summer Bay with his family and he and Duncan quickly become friends and get into various scrapes ."
            ]
        },
        {
            "input": "他此前曾效力过Wolverhampton Wanderers，Kidderminster Harriers，Mansfield Town，Lincoln City，Northampton Town，Chesterfield和Gateshead。",
            "output": [
                "He formerly played for Wolverhampton Wanderers , Kidderminster Harriers , Mansfield Town , Chesterfield , Northampton Town , Lincoln City and Gateshead ."
            ]
        },
        {
            "input": "独立的刘易斯学者凯瑟琳·林德斯科格（Kathryn Lindskoog）辩称，胡珀的奖学金并不可靠，而且他做了虚假陈述，并将伪造的作品归功于刘易斯。",
            "output": [
                "Kathryn Lindskoog , an independent Lewis scholar , argued that Hooper 's scholarship is not reliable and that he has made false statements and attributed false works ."
            ]
        },
        {
            "input": "体操和击剑（LP）以3-2获胜并留在甲级联赛。",
            "output": [
                "Gimnasia y Esgrima ( LP ) won with 3 -- 2 and stayed in the Primera División ."
            ]
        },
        {
            "input": "他于1858年毕业于舒门的加拉塔萨雷高中，并在伊斯坦布尔担任教师，直到1864年。",
            "output": [
                "In 1858 he graduated from the Galatasaray School in Schumen and became a teacher in Istanbul , where he remained until 1864 ."
            ]
        },
        {
            "input": "在209年早些时候，孙权孙与泉的妹妹孙女士结婚，以加强他与刘备的联盟。",
            "output": [
                "Earlier in 209 , Sun Quan married Sun Quan 's younger sister Lady Sun to strengthen the alliance between him and Liu Bei ."
            ]
        },
        {
            "input": "阿根廷政府在战争的最后几天保持中立，但却悄悄地容忍了1945年逃离德国，比利时和维希 - 法国的纳粹领导人的入境。",
            "output": [
                "The Argentine government remained neutral until the last days of war , but quietly tolerated the entry of Nazi leaders fleeing from Vichy , France , Belgium , and Germany in 1945 ."
            ]
        },
        {
            "input": "在他们的关系中，他们住在洛杉矶，虽然西摩在伦敦和洛杉矶的工作时间更长。",
            "output": [
                "Throughout her relationship , the couple lived in Los Angeles , though Seymour spent more time in London and Los Angeles for their work ."
            ]
        },
        {
            "input": "North Downs Way穿过Medway Valley Walk或高速公路桥东端的Medway高架桥。",
            "output": [
                "The North Downs Way crosses the Medway viaduct at the eastern end of Medway Valley Walk or the Autobahn bridge ."
            ]
        },
        {
            "input": "他取代了Archie Kao和Adam Rodriguez，也获得了人气。",
            "output": [
                "He also gained popularity by replacing Archie Kao with Adam Rodriguez ."
            ]
        },
        {
            "input": "根据美国人口普查局的统计，该市的总面积有土地，或1.35％是水。",
            "output": [
                "According to the United States Census Bureau , the town has a total area of , of which is land and , or 1.35 % , is water ."
            ]
        },
        {
            "input": "它位于新广场和新亨普斯特德以北，中提琴以东，春谷以南和新城以西。",
            "output": [
                "It is located north of New Square and New Hempstead , east of Viola , south of Spring Valley , and west of New City ."
            ]
        },
        {
            "input": "Pelmus已在罗马尼亚，法国，德国，以色列，加拿大，奥地利，智利和巴西的博物馆展出，包括五个个展。",
            "output": [
                "Pelmus has been exhibited in museums of Romania , France , Germany , Israel , Canada , Austria , Chile and Brazil , including five solo exhibitions ."
            ]
        },
        {
            "input": "欧文认为，他的乌托邦社区将根据他的优越社会，智力和体力改革的理想创造一个“社会环境”。",
            "output": [
                "Owen believed that his utopian community would create a \" social environment , based on his ideals of superior social , intellectual , and physical reform ."
            ]
        },
        {
            "input": "学校与自闭症学校Ysgol Plas Brondyffryn的中学部门建立了联系，该学院建于2003年。",
            "output": [
                "The school is in conjunction with the secondary department of the autistic school Ysgol Plas Brondyffryn , which was built in 2003 ."
            ]
        },
        {
            "input": "SR 164于1923年从Youngstown委托给Salineville。",
            "output": [
                "SR 164 was commissioned in 1923 , routed from Youngstown to Salineville ."
            ]
        },
        {
            "input": "2015年11月10日，ATP编辑Josh Meiseles在ATP世界巡回赛的最终网站上确认了8位选手的官方名单。",
            "output": [
                "On 10 November 2015 , ATP editor Josh Meiseles confirmed the official list of 8 players on the ATP World Tour final website ."
            ]
        },
        {
            "input": "芝加哥公立学校是位于伊利诺伊州芝加哥市北部的DeWitt Clinton学校。",
            "output": [
                "Chicago Public School is a DeWitt Clinton School on the northern side of Chicago , Illinois ."
            ]
        },
        {
            "input": "该公司当时收购了圣路易斯和狭窄的开罗铁路。",
            "output": [
                "The company then was the St. Louis and Cairo Railroad , which acquired narrow gauge ."
            ]
        },
        {
            "input": "他的父母是Don Luis Toranzos，他本人也是杰出的艺术家，而Angelina Miers来自阿根廷。",
            "output": [
                "His parents are Don Luis Toranzos , a prominent artist himself , and Angelina Miers , of Argentina ."
            ]
        },
        {
            "input": "由哥伦比亚广播公司制作或由CBS电影公司制作的1976年之前的大部分系列后来由维亚康姆和派拉蒙电视台发行。",
            "output": [
                "Most of the series produced by CBS before 1976 or distributed by CBS films were later distributed by Viacom and Paramount Television ."
            ]
        },
        {
            "input": "还有58架联络机，但其中20架仅用于信使。",
            "output": [
                "There were also 58 connecting aircraft , but 20 of these were used for messengers only ."
            ]
        },
        {
            "input": "它位于喜马偕尔邦（Tattapani），海拔650米，是治疗的理想温度。",
            "output": [
                "It is located in Tattapani ( Himachal Pradesh ) , at an altitude of 650mts , the perfect temperature for the treatments ."
            ]
        },
        {
            "input": "1815年，来自加利西亚的Amish Mennonites瑞士血统在Dubno附近定居。",
            "output": [
                "Amish Mennonites from Galicia with Swiss descent settled in 1815 near Dubno ."
            ]
        },
        {
            "input": "它有一所高中（“Cornway初级学院”）和一所托儿所（“Cornway Senior College”）。",
            "output": [
                "It has a high school ( \" Cornway Junior College \" ) and a preparatory school ( \" Cornway Senior College \" ) ."
            ]
        },
        {
            "input": "Bailey被Henry Cole取代为Breakheart Hill的看守。",
            "output": [
                "Bailey was succeeded as caretaker of Breakheart Hill by Henry Cole ."
            ]
        },
        {
            "input": "这是英国的洞穴列表，包括英国最大和最深的洞穴的信息。",
            "output": [
                "This is a list of caves in the United Kingdom , including information on the largest and deepest caves in the UK ."
            ]
        },
        {
            "input": "2016年2月，Souray与前WWE  - 专业摔跤运动员Barbara Blank结婚，后者更为人所知的是Kelly Kelly，他于2017年10月分居。",
            "output": [
                "Souray married former WWE professional wrestler Barbara Blank , better known as Kelly Kelly in February 2016 . They have separated in October 2017 ."
            ]
        },
        {
            "input": "轻小说是由Dojyomaru写的，由Fuyuyuki演绎并由Overlap Bunko出版。",
            "output": [
                "The light novels are written by Dojyomaru and illustrated by Fuyuyuki , and are published by Overlap Bunko ."
            ]
        },
        {
            "input": "Oraciu河或Orociu河是罗马尼亚Pustnic河的支流。",
            "output": [
                "The Oraciu River or Orociu River is a tributary of the Pustnic River in Romania ."
            ]
        },
        {
            "input": "在包括的12个故事中，有6个故事先发表在作者的第一个系列“晚间新闻”中。",
            "output": [
                "Of the twelve stories included , six were previously published in the author 's first collection , \" The Evening News \" ."
            ]
        },
        {
            "input": "他于1685年搬到魁北克，并在新法国生活了一段时间。",
            "output": [
                "He moved to Quebec around 1685 and lived in New France for some time ."
            ]
        },
        {
            "input": "戏剧演讲和公共艺术系最初由T. Earl Pardoe领导。",
            "output": [
                "The Dramatic and Public Arts Department was originally headed by T. Earl Pardoe ."
            ]
        },
        {
            "input": "据报道，苏塞克斯和兰辛学院于1860年11月参加过足球比赛，这是布莱顿公立学校的第一次。",
            "output": [
                "Sussex and Lancing Colleges , which played a football match in November 1860 , are recorded as the first of public schools in Brighton ."
            ]
        },
        {
            "input": "“Bonne Citoyenne”不幸在暴风雨中遭到破坏，并与法国中队的其他人分开。",
            "output": [
                "\" Bonne Citoyenne \" had the misfortune to be damaged in a storm and separated from the rest of the French squadron ."
            ]
        },
        {
            "input": "他在纽约市担任计算机顾问和软件工程师多年，然后于1998年搬到亚特兰大。",
            "output": [
                "He spent several years in New York City as a computer consultant and software engineer and moved to Atlanta in 1998 ."
            ]
        },
        {
            "input": "Kevin Lepage排名第三，Terry Labonte排名第四，Robby Gordon排名第五。",
            "output": [
                "Kevin Lepage started third , Terry Labonte fourth , and Robby Gordon qualified fifth ."
            ]
        },
        {
            "input": "2006年12月，Muspratt被John von Rhein和经典中的“芝加哥论坛报”的工作人员评为“年度最佳芝加哥人”。",
            "output": [
                "In December 2006 , Muspratt was named \" Chicagoan of the Year \" in classical music by John von Rhein and the staff of the \" Chicago Tribune \" ."
            ]
        },
        {
            "input": "他在1813年赢得了第一届罗马大奖的绘画，并于1814年以第二届罗马大奖的形式赢得了他对“Diagoras之死”的绘画。",
            "output": [
                "He won the first Prix de Rome for painting in 1813 and in 1814 the second Prix de Rome for his paintings of the \" death of the Diagoras \" ."
            ]
        },
        {
            "input": "Contempo Magazine是一份每月印刷版和每日在线美国杂志，发表于德克萨斯州麦卡伦。",
            "output": [
                "Contempo Magazine is a monthly American print and online magazine in McAllen , Texas ."
            ]
        },
        {
            "input": "费马 - 点的等幂共轭是正交点，反之亦然。",
            "output": [
                "The isodynamic conjugates of the Fermat points are the isogonal points and vice versa ."
            ]
        },
        {
            "input": "分支抄本2每天更新，分支抄本3每6个月更新一次。",
            "output": [
                "The codice 2 branch is updated daily , and the branch codice 3 is updated every 6 months ."
            ]
        },
        {
            "input": "这座房子于1858年由Dunira的David Dundas爵士购买，并于1864年从Cheshire的Lymm出售给George Dewhurst。",
            "output": [
                "The house was purchased by Sir David Dundas of Dunira in 1858 , who sold it on to George Dewhurst of Lymm , Cheshire , in 1864 ."
            ]
        },
        {
            "input": "杰特是罗马尼亚斯利维河的支流。",
            "output": [
                "The Jieţ is a tributary of the Slivei River in Romania ."
            ]
        },
        {
            "input": "Togdheer（索马里'Wabi Togdheer'）是索马里兰东部Togdheer河地区的一条季节性河流。",
            "output": [
                "Togdheer ( Somali \" Wabi Togdheer \" ) is a seasonal river in the Togdheer River region of eastern Somaliland ."
            ]
        },
        {
            "input": "2017年6月9日，在Vitaliy Levchenko加入Krylia Sovetov的教练组之后，Barkchi任命Mubin Ergashev为他们的经理。",
            "output": [
                "On 9 June 2017 , Barkchi Mubin Ergashev appointed her manager after Vitaliy Levchenko joined the Krylia Sovetov coaching staff ."
            ]
        },
        {
            "input": "Alycia Moulton以6比0,7比5击败Billie Jean King。",
            "output": [
                "Alycia Moulton defeated Billie Jean King 6 -- 0 , 7 -- 5 ."
            ]
        },
        {
            "input": "在接下来的一年里，Butcher回归并被Ian Rotten轮流淘汰出局。",
            "output": [
                "Butcher returned the following year and was eliminated in round two by Ian Rotten ."
            ]
        },
        {
            "input": "1725年3月6日，圣约翰与格林威治的伊丽莎白克劳利（安布罗斯克劳利的女儿）结婚。他们的孩子是：",
            "output": [
                "St John married Elizabeth Crowley ( the daughter of Ambrose Crowley ) of Greenwich on 6 March 1725 . Their children included :"
            ]
        },
        {
            "input": "Malhar Joshi不应该与作者Waman Gopal Joshi混淆，他们是同时代人。",
            "output": [
                "Vaman Malhar Joshi should not be confused with the writer Waman Gopal Joshi . They were contemporaries ."
            ]
        },
        {
            "input": "这部电影是在加利福尼亚州坎蒂尔的红岩峡谷州立公园（加利福尼亚州）拍摄的。",
            "output": [
                "The film was shot in California ( Red Rock Canyon State Park ) in Cantil , California ."
            ]
        },
        {
            "input": "Tweenies由Bella，Milo，Fizz，Jake，Doodles，Izzles，Max，Judy组成，有时加入Max的妹妹Polly。",
            "output": [
                "The tweenies consist of Bella , Milo , Fizz , Jake , Scribbles , Izzles , Max , Judy and are sometimes joined by Max 'apos ; Sister Polly ."
            ]
        },
        {
            "input": "Hector Crawford是3DB经理和管理员Curteis Crawford的兄弟，也是Dorothy Crawford的兄弟。",
            "output": [
                "Hector Crawford was brother of 3DB manager and administrator Curteis Crawford , and also brother of Dorothy Crawford ."
            ]
        },
        {
            "input": "Chad Ochocinco（1978年出生;前Chad Johnson）是美国足球界的接球手。",
            "output": [
                "Chad Ochocinco ( born 1978 ; formerly Chad Johnson ) is an American - American - football receiver ."
            ]
        },
        {
            "input": "沿着日本太平洋沿岸从伊豆半岛到九州观测到海啸，并记录了从夏威夷到阿拉斯加的潮汐。",
            "output": [
                "The tsunami was observed along the Pacific coast of Japan from Izu Peninsula to Kyushu , and recorded by tide gauges from Hawaii to Alaska ."
            ]
        },
        {
            "input": "世界上第一台激光器是由美国科学家Nikolay Basov和Alexander Prokhorov以及俄罗斯科学家Charles H. Townes于1960年开发的。",
            "output": [
                "In 1960 , the world 's first laser was developed by American scientists Nikolay Basov and Alexander Prokhorov , and Russian scientist Charles H. Townes ."
            ]
        },
        {
            "input": "这是伦敦考文特花园区街道名称的词源列表。",
            "output": [
                "This is a list of the etymology of street names in the district Covent Garden in London ."
            ]
        },
        {
            "input": "音乐由A. T. Ummer创作，歌词由Koorkkancheri Sugathan和Poovachal Khader编写。",
            "output": [
                "The music was composed by A. T. Ummer and lyrics were written by Koorkkancheri Sugathan and Poovachal Khader ."
            ]
        },
        {
            "input": "他们进入Aparan，Kotayk，并逐渐出现，于4月2日占领了埃里温。",
            "output": [
                "They entered Aparan , Kotayk and gradually emerging , captured Yerevan on April 2 ."
            ]
        },
        {
            "input": "根据2002年国家统计局的人口普查，托尔滕的居民面积为11,216人（男性5,827人，女性5,389人）。",
            "output": [
                "According to the 2002 census of the National Statistics Institute , Toltén has an area of 11,216 inhabitants ( 5,827 men and 5,389 women ) ."
            ]
        },
        {
            "input": "另一个系列赛在辛辛那提红军队和波士顿红袜队之间在哈瓦那举行。",
            "output": [
                "In Havana , another series was played between Cincinnati Reds and the Boston Red Sox ."
            ]
        },
        {
            "input": "SDUU目前在斯德哥尔摩，哥德堡，哈尔姆斯塔德，卡尔马，斯科讷，厄勒布鲁，于默奥，谢莱夫特奥和皮特奥设有分支机构。",
            "output": [
                "SDUU currently has local branches in Skåne , Örebro , Umeå , Halmstad , Kalmar , Stockholm , Göteborg , Skellefteå and Piteå ."
            ]
        },
        {
            "input": "南臂镇位于沙勒沃伊斯县南部，南部和西部与安特里姆郡接壤。",
            "output": [
                "South Arm Township is located in southern Charlevoix County and is bordered by Antrim County to the south and west ."
            ]
        },
        {
            "input": "容器玻璃具有较高含量的氧化镁和氧化钠作为平板玻璃和较低含量的二氧化硅，氧化钙和氧化铝。",
            "output": [
                "Container glass has a higher magnesium oxide and sodium oxide content than flat glass , and a lower Silica , Calcium oxide , and Aluminum oxide content ."
            ]
        },
        {
            "input": "他为Henry David Thoreau，Thomas Cholmondeley的朋友和Theodore Parker的“Parker”命名为“Thomas”。",
            "output": [
                "He was named \" Thomas \" for Henry David Thoreau 's friend , Thomas Cholmondeley and \" Parker \" for Theodore Parker ."
            ]
        },
        {
            "input": "现在解决公式31的冷漠出价以解决问题。",
            "output": [
                "Now to solve the indifference bid price find for formula _ 31 ."
            ]
        },
        {
            "input": "换句话说，“死”或“记住你会记住”。",
            "output": [
                "In other words , \" die death \" or \" remember that you will remember \" ."
            ]
        },
        {
            "input": "在罗杰去世后，他的儿子 - 林肯伯爵威廉·德·罗马雷继承了庄园。",
            "output": [
                "After Roger 's death , his son inherited -- William de Roumare , Earl of Lincoln -- the manor house ."
            ]
        },
        {
            "input": "旧的高中成为高中，而新的大楼变成了低等学校。",
            "output": [
                "The old grammar school became the Upper School while the new building became the Lower School ."
            ]
        },
        {
            "input": "该节日的主要合作伙伴是瑞银，庄园，喜力，Vaudoise Assurances和Parmigiani Fleurier。",
            "output": [
                "The main partners of this festival are Parmigiani Fleurier , Manor , Heineken , Vaudoise and UBS ."
            ]
        },
        {
            "input": "1975年3月19日，NFL在檀香山举行的所有权会议上授予加利福尼亚州帕萨迪纳超级碗XI。",
            "output": [
                "The NFL awarded Super Bowl XI to Pasadena , California on March 19 , 1975 at the owners ' meetings held in Honolulu ."
            ]
        },
        {
            "input": "Charley Frazier（1939年8月12日出生于德克萨斯州休斯顿）是美国橄榄球联盟和美国橄榄球联盟的前美国足球广泛接收者。",
            "output": [
                "Charley Frazier ( born August 12 , 1939 in Houston , Texas ) is a former American football receiver in the American Football League and the NFL ."
            ]
        },
        {
            "input": "Belson作为音频导演编写了现场动态视觉效果和Jacobs编程的电子音乐和视觉实验。",
            "output": [
                "Belson as audio director programmed kinetic live visuals , and Jacobs programmed electronic music and visual experiments ."
            ]
        },
        {
            "input": "导演Larysa Malyukova和电影评论家Amir Yatsiv讨论了罕见的动画电影类型。",
            "output": [
                "A film director Larysa Malyukova and film critic Amir Yatsiv discussed the rare genre of the animated documentary ."
            ]
        },
        {
            "input": "它于1941年7月28日推出，并于8月完成。",
            "output": [
                "She was launched on 28 July 1941 and completed in August ."
            ]
        },
        {
            "input": "它是自由攀爬的，并在1938年首次攀登时以Bill House的名字命名。",
            "output": [
                "It was free climbed and named after Bill House , when he first climbed it in 1938 ."
            ]
        },
        {
            "input": "在Hedwig和The Angry Inch的舞台版和电影版中，海德薇的角色在离开Junction City后都会吸引到东德。",
            "output": [
                "In both the stage and film version of Hedwig and the Angry Inch , the character of Hedwig moves to East Germany after leaving Junction City ."
            ]
        },
        {
            "input": "他是一位雕塑家，他创作了几件具有纪念意义的雕塑作品，包括获奖的“哨兵”。",
            "output": [
                "He is a sculptor who has designed several monumental sculptures , including the award-winning \" Sentinel \" ."
            ]
        },
        {
            "input": "英语也有很多单词，例如'zillion``，它们被非正式地用于表示无限期和虚构但未指明的数量，看到大量数字。",
            "output": [
                "English also has many words , such as \" zillion \" , used informally to mean indefinite and fictitious but unspecified amounts ; see large numbers ."
            ]
        },
        {
            "input": "Ryan Sweeting在决赛中以6比4,6比3战胜埃文斯。",
            "output": [
                "Ryan Sweeting won against Evans in the final 6 -- 4 , 6 - 3 ."
            ]
        },
        {
            "input": "它于2010年4月23日至29日在西班牙加泰罗尼亚巴塞罗那的巴塞罗那皇家俱乐部举行。",
            "output": [
                "It took place from 23 April to 29 April 2010 in the Real Club de Tenis Barcelona in Catalonia , Barcelona , Spain ."
            ]
        },
        {
            "input": "意大利教堂St. Giovanni Bosco以圣约翰博斯科命名。",
            "output": [
                "The Italian St. Giovanni Bosco Church is named after St. John Bosco ."
            ]
        },
        {
            "input": "Castlebrae社区高中是Greendykes爱丁堡地区的一所中学。",
            "output": [
                "Castlebrae Community High School is a secondary school located in the area of Greendykes in Edinburgh ."
            ]
        },
        {
            "input": "1819年8月31日，沃斯通克拉夫特号在悉尼船上抵达格林纳达。",
            "output": [
                "Wollstonecraft arrived on August 31 , 1819 on board the ship \" Sydney \" in Grenada ."
            ]
        },
        {
            "input": "在许多省份，清真寺遭到轰炸，回族被日军屠杀或摧毁。",
            "output": [
                "Mosques were bombed and in many provinces Hui were slaughtered by Japanese troops or destroyed ."
            ]
        },
        {
            "input": "图灵有一个哥哥，约翰德莫特图灵（约翰爵士的父亲，图灵男爵的第12个男爵）。",
            "output": [
                "Turing had an elder brother , John Dermot Turing ( the father of Sir John , 12th Baronet of the Turing baronets ) ."
            ]
        },
        {
            "input": "该网络以前在Waterbury，W12B​​H（第12频道）运营翻译，直接重复WEDY。",
            "output": [
                "The network previously run a translator in Waterbury , W12BH ( Channel 12 ) , which repeated WEDY directly ."
            ]
        },
        {
            "input": "Blauvelt家族于1638年首次抵达罗克兰县，并于1683年首次抵达美国。",
            "output": [
                "The Blauvelt family arrived in Rockland County for the first time in 1638 and first arrived in America in 1683 ."
            ]
        },
        {
            "input": "Buccinum parvulum是一种海洋蜗牛，是Buccinidae家族中真正的腹足动物软体动物。",
            "output": [
                "Buccinum parvulum is a species of sea snail , a true gastropod mollusk in the family Buccinidae , the marine whelks ."
            ]
        },
        {
            "input": "ISPS Handa推广残疾人高尔夫和盲人高尔夫，并与当地高尔夫协会合作，为众多锦标赛提供全球管理和财务支持。",
            "output": [
                "ISPS Handa promotes blind golf and disabled golf , and provides management and financial support to a number of tournaments in cooperation with the local golf associations worldwide ."
            ]
        },
        {
            "input": "Dinesh Gunawardena的兄弟和Philip Gunawardena的长子，他在科伦坡皇家学院接受教育。",
            "output": [
                "The brother of Dinesh Gunawardena and the eldest son of Philip Gunawardena , he was educated at the Royal College , Colombo ."
            ]
        },
        {
            "input": "莫顿是沙夫茨伯里议会议员约翰莫顿的儿子，也是坎特伯雷大主教威廉莫顿的侄子。",
            "output": [
                "Morton was son of John Morton , Member of Parliament for Shaftesbury , and the nephew of William Morton , the Archbishop of Canterbury ."
            ]
        },
        {
            "input": "1872年，詹姆斯爵士与约翰·奈恩·福尔曼（1929年12月20日）结婚，是海伦·玛格丽特·冯·斯塔塔的女儿。",
            "output": [
                "Sir James married , in 1872 , John Nairne Forman ( d. 20 December 1929 ) , daughter of Helen Margaret of Staffa , WS ."
            ]
        },
        {
            "input": "正式地，Bridgeville是Rock Hill的一部分。",
            "output": [
                "Bridgeville was formally part of Rock Hill ."
            ]
        },
        {
            "input": "2000年7月1日起，Mineral Hills村和Stambaugh市与Iron River市合并。",
            "output": [
                "Effective July 1 , 2000 , the village of Mineral Hills and the city of Stambaugh were consolidated with the city of Iron River ."
            ]
        },
        {
            "input": "Easthope于1784年10月29日出生于图克斯伯里，是Thomas Easthope的长子，他是伍斯特郡Overbury的John Leaver的女儿。",
            "output": [
                "Easthope , born on 29 October 1784 in Tewkesbury , was the eldest son of Elizabeth by Thomas Easthope , daughter of John Leaver from Overbury , Worcestershire ."
            ]
        },
        {
            "input": "他后来加入了第25军团，第8军团，并于1865年以第11位husaren的军衔结束了他的军事生涯。",
            "output": [
                "He later joined the 25th Regiment of Foot , 8th Hussars and ended his military career , in 1865 , with the rank of major in the 11th Hussars ."
            ]
        },
        {
            "input": "这些航空公司连接印度80多个城市，并在印度航空自由化后运营海外航线。",
            "output": [
                "These airlines connect more than 80 cities across India and also operate overseas routes following the liberalisation of Indian aviation ."
            ]
        },
        {
            "input": "Google允许企业主检查自己的业务数据，并且还招募志愿者来验证和纠正土壤止赎数据。",
            "output": [
                "Google allows business owners to check their own business data , and has also recruited volunteers to verify and correct ground truth data ."
            ]
        },
        {
            "input": "此外，许多Angika发言人已移民到波斯湾，美国，加拿大，英国和其他国家。",
            "output": [
                "Moreover , many Angika speakers in the Persian Gulf have emigrated to the United Kingdom , the United States , Canada , and other countries ."
            ]
        },
        {
            "input": "音乐由Darsan Raman和Mariamma Philip编写的歌词组成。",
            "output": [
                "The music was composed by Darsan Raman and lyrics was written by Mariamma Philip ."
            ]
        },
        {
            "input": "在特定搜索树中搜索二进制密钥可以递归地或迭代地编程。",
            "output": [
                "Searching a specific search tree according to a binary key can be recursively or iteratively programmed ."
            ]
        },
        {
            "input": "在纽约的伦纳德和格里菲斯之间的会议之后，格里菲斯飞往洛杉矶并拍摄了这一集。",
            "output": [
                "Following conferences between Leonard and Griffith in New York , Griffith flew to Los Angeles and filmed the episode ."
            ]
        },
        {
            "input": "2009年7月7日，弗朗西斯·奥凯洛少将取代少将纳丹·穆吉沙担任非索特派团指挥官。",
            "output": [
                "On July 7 , 2009 , General Major Nathan Mugisha was replaced as Commander of AMISOM by the general major Francis Okello ."
            ]
        },
        {
            "input": "Ricky决定为Nate而战，并证实了他对她的爱。",
            "output": [
                "Ricky decides to fight for Nate and confirmed his love for her ."
            ]
        },
        {
            "input": "Kathy Rinaldi以6比1,6比3击败了Bonnie Gadusek。",
            "output": [
                "Kathy Rinaldi defeated Bonnie Gadusek 6 -- 1 , 6 -- 3 ."
            ]
        },
        {
            "input": "1979-80赛季的全国篮球协会赛季是NBA的第34个赛季。",
            "output": [
                "The NBA season between 1979 and 80 was the 34th season of the National Basketball Association ."
            ]
        },
        {
            "input": "这里可能不包括一些希伯来语和亚拉姆语缩写，更多可以在阿拉姆语缩写列表或希伯来语缩写列表中找到。",
            "output": [
                "Some Hebrew and Aramaic abbreviations may not be included here , and more can be found in the list of Hebrew abbreviations or in the list of Aramaic abbreviations ."
            ]
        },
        {
            "input": "这个系列是沃尔玛加拿大独有的，但是在Spawn商店在线销售。",
            "output": [
                "This series was exclusive to Wal-Mart Canada but was eventually sold in the Spawn Store online ."
            ]
        },
        {
            "input": "半线性变换是一种线性“直到扭曲”的变换，意思是“直到标量乘法下的场自同构”。",
            "output": [
                "A semilinear transformation is a transformation that is \" up to a twist \" linear , which means \" to a field automorphism under scalar multiplication \" ."
            ]
        },
        {
            "input": "Aguiari将其描述为“在交通中间独自行动，但在那里有一座禅宗雕像”。",
            "output": [
                "Aguiari described it as \" a nice action in the middle of traffic alone , but up there with a Zen - statue \" ."
            ]
        },
        {
            "input": "伦纳德和麦当娜在合唱中添加了西班牙语短语，在第二节经文中添加了西班牙语短语，并在中间增加了乐器突破。",
            "output": [
                "Leonard and Madonna had added Spanish phrases in the chorus , about the trumpets of the second verse and also in the added instrumental fracture in the middle ."
            ]
        },
        {
            "input": "Olin M. Jeffords的儿子，担任佛蒙特州最高法院首席大法官，出生于佛蒙特州拉特兰的James Jeffords。",
            "output": [
                "The son of Olin M. Jeffords , who served as Chief Justice of the Vermont Supreme Court , James Jeffords was born in Rutland , Vermont ."
            ]
        },
        {
            "input": "他目前的研究调查了犹太人的思想和故事对伊斯兰资源的影响。",
            "output": [
                "His current research explores the influence of Jewish ideas and stories on Islamic sources ."
            ]
        },
        {
            "input": "术语“非遗传性球形细胞增多症”虽然偶尔使用，但很少使用。",
            "output": [
                "The term \" non-hereditary spherocytosis \" is rarely used , albeit occasionally ."
            ]
        },
        {
            "input": "英格兰的Dingwall和Tingwall，挪威的Thingwall，马恩岛的Tynwald和苏格兰的Tingvoll都有相同的根和名字。",
            "output": [
                "Dingwall and Tingwall in England , Thingwall in Norway , Tynwald on the Isle of Man , and Tingvoll in Scotland bear names of the same root and meaning ."
            ]
        },
        {
            "input": "这是为英国伦敦服务的各种地方政府组织负责人名单。",
            "output": [
                "This is a list of the various heads of the local governmental organisations that have served London , England ."
            ]
        },
        {
            "input": "从1866年到1928年，当父权制席位被移至黎巴嫩贝鲁特时，这个帝国主义是西里西亚亚美尼亚天主教家长的所在地。",
            "output": [
                "From 1866 to 1928 , eparchy was the seat of the Armenian Catholic Patriarchate of Cilicia until the patriarchal seat of Beirut was moved to Lebanon ."
            ]
        },
        {
            "input": "该节日成立于2007年，在亚利桑那州凤凰城首次亮相，此后一直在圣地亚哥，休斯敦和苏黎世举行。",
            "output": [
                "The festival originated in 2007 and debuted in Phoenix , Arizona and has since been held in San Diego , Houston and Zurich ."
            ]
        },
        {
            "input": "之前的编辑包括Michel Foucault，Emmanuel Le Roy Ladurie，Georges Dumezil，Francois Jacob，Jacques Le Goff，Francois Furet和Raymond Aron。",
            "output": [
                "Past editors include Raymond Aron , Georges Dumézil , François Jacob , Michel Foucault , Emanuel Le Roy Ladurie , François Furet , and Jacques Le Goff ."
            ]
        },
        {
            "input": "Lucknow  -  Sitapur  -  Seramow省立铁路与Bareilly  -  Pilibheet省立铁路合并，于1891年1月1日组建勒克瑙 - 巴雷利铁路。",
            "output": [
                "The Lucknow -- Sitapur -- Seramow Provincial State Railway merged with the Bareilly -- Pilibheet Provincial State Railway to the Lucknow -- Bareilly railway on 1 January 1891 ."
            ]
        },
        {
            "input": "专门的感觉链纤维是肌肉中含有的核器官。",
            "output": [
                "A specialized sensory chain fiber is a nuclear organ contained within a muscle ."
            ]
        },
        {
            "input": "两年后，伯德于1970年与布朗重聚。",
            "output": [
                "After two years , Byrd reunited with Brown in 1970 ."
            ]
        },
        {
            "input": "假设因果关系是线性的，这种背景知识可以用以下结构方程模型（SEM）规范表示。",
            "output": [
                "Assuming that the causal relationships are linear , this background knowledge can be expressed in the following SEM specification ( Structural Equalization Model ) ."
            ]
        },
        {
            "input": "Sympatric食肉动物包括山狮，美洲黑熊和灰熊。",
            "output": [
                "Sympatric - predators include the mountain lion , the American black bear and the grizzly bear ."
            ]
        },
        {
            "input": "该市东半部大部分地区相对农村，而城市的西部（大致来自伍德伯里角东部）更加城市化。",
            "output": [
                "Most of the eastern half of the city is relatively rural , while the western part of the city is more urbanized ( for example , from Woodbury Point east ) ."
            ]
        },
        {
            "input": "在1956年夏天，Mike Barnett接替了Frank Lovejoy的角色，直到同年结束。",
            "output": [
                "In the summer of 1956 , Mike Barnett took over the role of Frank Lovejoy until the end of the series in that same year ."
            ]
        },
        {
            "input": "纽约州南部亨廷顿（North Huntington）北面110号，在沃尔特惠特曼商店（Walt Whitman Shops）的小村庄与纽约25号（西耶利哥收费公路）进入一个等级交叉口。",
            "output": [
                "North of South Huntington , NY 110 enters an at-grade crossing with NY 25 ( West Jericho Turnpike ) in the hamlet of Walt Whitman Shops ."
            ]
        },
        {
            "input": "Tabda，也被称为Tabto，是索马里南部Jubbada Hoose（下朱巴）地区的一个小镇。",
            "output": [
                "Tabda , also known as Tabto , is a city in the southern Jubbada Hoose ( Lower Juba ) region of Somalia ."
            ]
        },
        {
            "input": "他于1866年被分配到朴茨茅斯海军造船厂，然后于1868年被派往彭萨科拉海军造船厂。",
            "output": [
                "It was assigned to the Portsmouth Navy Yard in 1866 , and then to the Pensacola Navy Yard in 1868 ."
            ]
        },
        {
            "input": "他于2008年2月离开了Janata Dal（联合国）并进入了印度人民党（Bharatiya Janata Party）。",
            "output": [
                "He left the Janata Dal ( United ) and joined the Bharatiya Janata Party in February , 2008 ."
            ]
        },
        {
            "input": "一个中等的马其顿犹太人社区在地中海沿岸有很长的存在，特别是在以色列北部和Gush Dan。",
            "output": [
                "A small-medium Macedonian Jewish community has a very long presence on the Mediterranean coast , especially in Gush Dan and northern Israel ."
            ]
        },
        {
            "input": "Bota Mare河是罗马尼亚Zăbrătău河的支流。",
            "output": [
                "The Bota Mare River is a tributary of the Zăbrătău River in Romania ."
            ]
        },
        {
            "input": "尼克史密斯（克里斯伊根）与他的家人在夏日湾定居，他和邓肯很快结交朋友并陷入各种危机。",
            "output": [
                "Chris Egan ( Nick Smith ) settles with his family in Summer Bay and he and Duncan quickly become friends and get into different scratches ."
            ]
        },
        {
            "input": "他们配备了一条白色皮革围裙，长长的手套和一把手柄安装在黄铜上的斧头。",
            "output": [
                "They were equipped with a white leather apron , long gauntlet gloves , and an axe with a brass mounted handle ."
            ]
        },
        {
            "input": "在2017赛季，康奈尔大红队赢得了649场比赛，并列529场比赛，并且输掉了33场常规赛。",
            "output": [
                "Throughout the 2017 season , the Cornell Big Red have won 649 games , 529 games bound and 33 regular season games lost ."
            ]
        },
        {
            "input": "Andrea Bocelli称她的排练表演“非常好”，大卫福斯特称她的声音很壮观。",
            "output": [
                "Andrea Andrea Bocelli called her sample performance \" very nice \" , and David Foster called her voice spectacular ."
            ]
        },
        {
            "input": "麦克斯威尼出生于北爱尔兰，后来移居伦敦。",
            "output": [
                "McSweeney was born in Northern Ireland but moved to London ."
            ]
        },
        {
            "input": "11月，Royals CF Coco Crisp从波士顿红袜队获得了RPRamónRamírez。",
            "output": [
                "In November , the Royals acquired CF Coco Crisp from the Boston Red Sox in exchange for RP Ramón Ramírez ."
            ]
        },
        {
            "input": "这项工作使他引发了对分子遗传学和基因组学实践的重要思考，而这一点并不符合道德规范。",
            "output": [
                "This work caused him to trigger important reflections on the practices of molecular genetics and genomics at a time when this was not considered ethical ."
            ]
        },
        {
            "input": "例如，在JavaScript中，因子函数可以通过这样的递归定义为匿名：",
            "output": [
                "For example , in JavaScript the factorial function can be defined via such recursion as anonymous :"
            ]
        },
        {
            "input": "维也纳冰雕在大多数欧洲国家巡回演出，包括德国，意大利，荷兰，瑞士，匈牙利，捷克斯洛伐克，比利时，法国和西班牙。",
            "output": [
                "The Vienna Ice Revue toured through most European countries including Germany , Italy , the Netherlands , Switzerland , Hungary , Czechoslovakia , Belgium , France and Spain ."
            ]
        },
        {
            "input": "在1406年，他添加了Dioscurides的朱莉安娜Anicia法典，反弹和目录以及拜占庭希腊语中的Minuskel scholia广泛修复。",
            "output": [
                "In 1406 he had the Juliana Anicia Codex of Dioscurides added , rebound , and a table of contents and minuscule scholia restored in Byzantine Greek extensive ."
            ]
        },
        {
            "input": "1927年8月，毛泽东结束了与杨的婚姻;并且，在1928年初，他开始与何子珍建立关系。",
            "output": [
                "In August 1927 , Mao ended his marriage with Yang and started a relationship with He Zizhen in early 1928 ."
            ]
        },
        {
            "input": "他在纽约巨人队和西雅图海鹰队之间的赛季中完成了他的NFL职业生涯。",
            "output": [
                "He finished his NFL career in , splitting the season between the New York Giants and the Seattle Seahawks ."
            ]
        },
        {
            "input": "Neptunea alexeyevi是一种海螺，是Buccinidae家族中真正的腹足动物软体动物。",
            "output": [
                "Neptunea alexeyevi is a species of sea snail , a true gastropod mollusk in the family Buccinidae , the marine whelks ."
            ]
        },
        {
            "input": "这是他们第三次击中第一首“桃子”，Linda Greene。",
            "output": [
                "It was their third hit with the first \" Peaches \" , Linda Greene ."
            ]
        },
        {
            "input": "当Patrick Logan到达Wisteria Lane时，他跑过Nick。",
            "output": [
                "When Patrick Logan arrives to Wisteria Lane , he runs Nick over ."
            ]
        },
        {
            "input": "他有两个儿子：年长的Maharana Mahendra Singh和年轻的Arvind Singh。",
            "output": [
                "He has two sons : elder Maharana Mahendra Singh and younger Arvind Singh ."
            ]
        },
        {
            "input": "Virgil Weigel是堪萨斯州众议院的民主党成员，代表第56区（堪萨斯州托皮卡的堪萨县肖尼县）。",
            "output": [
                "Virgil Weigel is democratic member of the House of Representatives of Kansas and represents the 56th district ( Shawnee County , Kansas in Topeka , Kansas ) ."
            ]
        },
        {
            "input": "这个物种可以在巴布亚新几内亚，俾斯麦群岛：新英国;伍德拉克岛;西巴布亚;阿鲁群岛。",
            "output": [
                "This species can be found in New - Britannia , Bismarck - archipelago : Woodlark Island , Papua - New Guinea , West Papua and Aru - Islands ."
            ]
        },
        {
            "input": "忽必烈为中国学者建立了学校，花了纸币，恢复了儒家仪式，并支持刺激农业和商业增长的政策。",
            "output": [
                "Kublai built schools for Chinese scholars , issued paper money , revived Confucian rituals , and endorsed policies that stimulated agricultural and commercial growth ."
            ]
        },
        {
            "input": "“罗金厄姆”于5月23日抵达黄埔，于9月21日抵达孟买。",
            "output": [
                "\" Rockingham \" reached Whampoa on May 23 and arrived in Bombay on September 21 ."
            ]
        },
        {
            "input": "在卡迪夫大学和北约克郡哈罗盖特完成大学学业后，他于1996年至1999年在法国鲁昂工作。",
            "output": [
                "After completing his initial university education at Cardiff University , and in Harrogate , North Yorkshire , he was from 1996 to 1999 based in Rouen , France ."
            ]
        },
        {
            "input": "我在西德尼诺兰风景中创造了弗朗西斯培根人物，灵感来自让科克托的特技。",
            "output": [
                "I created Francis Bacon figures in a Sidney Nolan landscape , with stunts inspired by Jean Cocteau. \""
            ]
        },
        {
            "input": "相反，他们可能是亲戚，也许是血缘关系的家庭成员，为德古拉服务。",
            "output": [
                "They could have been relatives instead , perhaps members of a family connected by blood to serve Dracula ."
            ]
        },
        {
            "input": "两所中学，Heatherhill中学和Coomoora中学，与Springvale中学和Chandler中学合并到Keysborough中学。",
            "output": [
                "The two secondary schools , Heatherhill Secondary College and Coomoora Secondary College have been merged with Springvale Secondary College and Chandler Secondary College into Keysborough Secondary College ."
            ]
        },
        {
            "input": "在抄本_4中，第二个文件是抄本_8，而在抄本_5中，第二个文件是抄本_10。",
            "output": [
                "In codice 4 is the second file codice 8 and codice 5 is the second file codice 10 ."
            ]
        },
        {
            "input": "1880年Edward Drinker Cope描述了“Pogonodon”，有两种物种：“P. davisi”和“P. platycopis”。",
            "output": [
                "\" Pogonodon \" was described in 1880 by Edward Drinker Cope . Two species are recognized , \" P. davisi \" and \" P. platycopis \" ."
            ]
        },
        {
            "input": "光学偏振在微观上由材料系统的不同状态之间的量子力学转变产生。",
            "output": [
                "Microscopically , the optical polarization arises from quantum mechanical transitions between different states of the material system ."
            ]
        },
        {
            "input": "其余两辆车由爱沙尼亚国防联盟交付，并于1927年订购。",
            "output": [
                "The remaining two cars were delivered by the Estonian Defence League and these were ordered in 1927 ."
            ]
        },
        {
            "input": "他还出演了音乐电影，后来出演了喜剧角色。",
            "output": [
                "He also appeared in musical films and later in life , in comedic roles ."
            ]
        },
        {
            "input": "弗雷德米勒于1998年去世，而约翰保罗米勒于2000年去世，玛丽米勒继续住在克利夫兰南部的房子里。",
            "output": [
                "Following the death of Fred Miller in 1998 and John Paul Miller in 2000 , Mary Miller continued to live in the house located south of Cleveland ."
            ]
        },
        {
            "input": "Glen Sheil出生于悉尼，年纪轻轻就搬到了昆士兰州。",
            "output": [
                "Glen Sheil was born in Sydney and moved to Queensland at a young age ."
            ]
        },
        {
            "input": "该节目同时在澳大利亚的Fox8，新西兰的Sky TV以及南非的O频道播出。",
            "output": [
                "The show was broadcasted simultaneously on Fox8 in Australia , Sky TV in New Zealand and on Channel O in South Africa ."
            ]
        },
        {
            "input": "莱曼冰川以克劳德·尤因腊斯克的名字命名威廉丹尼森莱曼，因为莱曼是第一个描述亚当山的一些特征和历史的人之一。",
            "output": [
                "Lyman Glacier was named after William Denison Lyman by Claude Ewing Rusk because Lyman was one of the first to describe some of Mount Adams ' features and history ."
            ]
        },
        {
            "input": "Dantès的朋友Fernand Mondego（Sidney Blackmer）陪伴他进监狱。",
            "output": [
                "Dantès ' friend Sidney Blackmer ( Fernand Mondego ) accompanies him to the jail ."
            ]
        },
        {
            "input": "英厄姆写道，1872年12月，大学报“阿尔戈纳大学生”报告了以下学费：",
            "output": [
                "Ingham wrote that in December , 1872 the college newspaper , the \" Algona Collegian \" reported the following tuition :"
            ]
        },
        {
            "input": "她被他吸引住了，并试图引诱他进入性关系，但是哈万特·辛格在思想上有宗教信仰并没有去乱伦。",
            "output": [
                "She grew heavily attracted to him and tried to seduce him into a sexual relationship , but Hanuvant Singh was religious in thought and did not go for incest ."
            ]
        },
        {
            "input": "这是他们突破“Smash”（1994）的第四首单曲和第三首单曲。",
            "output": [
                "It is the fourth track and third single from their breakthrough album \" Smash \" ( 1994 ) ."
            ]
        },
        {
            "input": "他于1949年考入纽约酒吧并开始在纽约市练习。",
            "output": [
                "In 1949 , he was admitted to the New York City Bar Association and began practice in New York ."
            ]
        },
        {
            "input": "作为一名苏联官方艺术家，他的作品深受广泛欢迎。",
            "output": [
                "As an official Soviet artist , his work was widely exhibited and well received ."
            ]
        },
        {
            "input": "Sambata河是罗马尼亚Caprei河的一条支流。",
            "output": [
                "The Sâmbăta river is a tributary of the River Piatra Caprei in Romania ."
            ]
        },
        {
            "input": "吉尔家族于1968年关闭了工厂，新业主于1980年将其出售。",
            "output": [
                "The Gill family closed the mill in 1968 and sold them to the new owners in 1980 ."
            ]
        },
        {
            "input": "俄克拉荷马市已将圣达菲站指定为城市和大都市区的多式联运服务地点。",
            "output": [
                "The city of Oklahoma City has designated Santa Fe railway station as the location for intermodal transit for the city and the greater area ."
            ]
        },
        {
            "input": "他在中英文学校上了夜班英语。",
            "output": [
                "At the Anglo-Chinese School he took night lessons on the English language ."
            ]
        },
        {
            "input": "他曾多次被选为阿萨姆足球协会和阿萨姆体育委员会主席，并且还是阿萨姆板球协会的副主席。",
            "output": [
                "He was elected President of the Assam Football Association and the Assam Sports Council for several terms ; he was also the Vice-President of the Assam Cricket Association ."
            ]
        },
        {
            "input": "Fădimac河是罗马尼亚贝加河的支流。",
            "output": [
                "The river Fădimac is a tributary of the River Bega in Romania ."
            ]
        },
        {
            "input": "Bertlmann是已故Walter Thirring的密友和合作者，并与John Stewart Bell一起工作。",
            "output": [
                "Bertlmann was close friend and collaborator of the late Walter Thirring and worked with John Stewart Bell ."
            ]
        },
        {
            "input": "这部电影的音乐由Vijaya Bhaskar和Chi Udaya Shankar和Vijaya Narasimha的配乐写成。",
            "output": [
                "The music of the film was composed by Vijaya Bhaskar and lyrics for the soundtrack written by Chi . Udaya Shankar and Vijaya Narasimha ."
            ]
        },
        {
            "input": "该社区的一部分被附属于圣克拉拉县，其余部分由圣何塞的非法人地区组成。",
            "output": [
                "Part of the neighborhood has been connected to Santa Clara County , while the rest consists of non-registered areas of San Jose ."
            ]
        },
        {
            "input": "这份手稿的工作始于1426年，由帖木儿王子Baysonghor Mirza命令，并于四年后的1430年完成。",
            "output": [
                "The work on this manuscript was started in 1426 on the orders of the Timurid Prince Baysonghor Mirza and completed four years later , in 1430 ."
            ]
        },
        {
            "input": "今天（从2013年到2017年），市长是费尔南多·诺盖拉，由PenCe（独立运动）选举产生。市政假日是10月1日。",
            "output": [
                "The present ( from 2013 to 2017 ) Mayor is Fernando Nogueira , elected by the PenCe ( independent movement ) . The municipal holiday is October 1 ."
            ]
        },
        {
            "input": "克罗克从密西西比州的纳奇兹搬到康科迪亚教区的总部维达利亚，并在黑河区穿越了下瓦希塔。",
            "output": [
                "Crocker moved from Natchez , Mississippi to Vidalia , the seat of Concordia Parish , and crossed toward the lower Ouachita in the section called the Black River ."
            ]
        },
        {
            "input": "Nar-Dos发展了亚美尼亚人的心理现实主义的批判趋势，展示了精致的亚美尼亚语。",
            "output": [
                "Nar-Dos developed the critical Armenian trend of psychological realism by displaying refined Armenian language ."
            ]
        },
        {
            "input": "她去世后与Edmund Ashfield和Richard Glanville结婚。",
            "output": [
                "She married Edmund Ashfield and after his death Richard Glanville ."
            ]
        },
        {
            "input": "在旅途的五天里，他带来了一些关于厄尔巴岛的书，他从枫丹白露学习。",
            "output": [
                "During the five days of the journey , he brought some books about Elba which he studied from Fontainebleau ."
            ]
        },
        {
            "input": "麻雀说服特纳，伊丽莎白可以用魔法指南针找到胸部。",
            "output": [
                "Sparrow convinces Turner that Elizabeth can be freed by using the magic compass to find the chest ."
            ]
        },
        {
            "input": "该联盟是阿根廷大布宜诺斯艾利斯Ezeiza Partido的一个城市。",
            "output": [
                "La Unión is a town in Ezeiza Partido , in the Greater Buenos Aires , Argentina ."
            ]
        },
        {
            "input": "1923年，独立成员约翰·阿奇博尔德·马哈格（John Archibald Maharg）担任反对党领袖，独立的哈里斯·特纳（Harris Turner）在1924年和1925年担任反对党领袖。",
            "output": [
                "In 1923 , John Archibald Maharg was an independent member of the opposition leader , and Harris Turner , also independent , served as opposition leader in 1924 and 1925 ."
            ]
        },
        {
            "input": "美国海军和国家公园管理局联合管理该纪念馆于1980年9月9日成立。",
            "output": [
                "The joint administration of the memorial by the National Park Service and the United States Navy was established on September 9 , 1980 ."
            ]
        },
        {
            "input": "Pérez还与Telemundo合作，在那里她为Telemundo Internacional建立了一个娱乐部门。",
            "output": [
                "Pérez also interned with Telemundo where she produced and anchored an entertainment segment for Telemundo Internacional ."
            ]
        },
        {
            "input": "在经过亚洲和非洲和欧洲的广泛旅行之后，这对夫妇定居在纽约的纽约市。",
            "output": [
                "After extensive traveling through Asia and a bit of Africa and Europe , the couple settled in New York City , New York ."
            ]
        },
        {
            "input": "Mouhoun是Boucle du Mouhoun地区的45个省之一，位于布基纳法索。 Mouhoun的首府是Dédougou。",
            "output": [
                "Mouhoun is one of 45 provinces in the Boucle du Mouhoun region and is located in Burkina Faso , the capital of Mouhoun is Dédougou ."
            ]
        },
        {
            "input": "它位于西澳大利亚州Moora地区的石英岩山丘上，靠近Wheatbelt，生长在沙质土壤中，通常带有砾石。",
            "output": [
                "It is found on Quartzite hills in the Moora region of Western Australia near Wheatbelt , where it is often grown with gravel in sandy soils ."
            ]
        },
        {
            "input": "该村有三所学校 - 一所小学和两所中学。",
            "output": [
                "The village has three schools -- a primary and two secondary schools ."
            ]
        },
        {
            "input": "2016年2月，丹尼尔波拉克宣布阿根廷与保罗辛格达成协议。",
            "output": [
                "Daniel Pollack announced in February 2016 that Argentina had reached an agreement with Paul Singer ."
            ]
        },
        {
            "input": "治疗包括渐进性肌肉松弛，认知暴露疗法和内部组织重建，或两者的组合。",
            "output": [
                "The treatment included progressive muscle relaxation , cognitive exposure therapy with interoceptive restructuring , or a combination of both ."
            ]
        },
        {
            "input": "冲锋枪是一种巨大的长矛，它可以“形成一个锋利的有机刀刃，可以用来攻击敌人。",
            "output": [
                "The Charge Spear is a large spear that can be \" charged \" to form a sharpened organic blade that can be used to stab foes ."
            ]
        },
        {
            "input": "酒店毗邻希克斯特德（Hickstead）小村庄，位于伯吉斯山（Burgess Hill）西部，毗邻从伦敦到布莱顿（Brighton）的主要A23公路。",
            "output": [
                "It is located next to the hamlet of Hickstead , to the west of Burgess Hill and adjacent to the main road A23 from London to Brighton ."
            ]
        },
        {
            "input": "Hidalgo出生于塞维利亚，效力于巴达霍斯和塞尔维德维戈。",
            "output": [
                "Hidalgo was born in Seville , who played for Badajoz and Celta de Vigo ."
            ]
        },
        {
            "input": "哈丁独立学区是位于德克萨斯州哈丁（美国）的公立学区。",
            "output": [
                "Hardin Independent School District is a public school district located in Hardin , USA ( Texas ) ."
            ]
        },
        {
            "input": "巴兹加河是罗马尼亚博霍廷河的支流。",
            "output": [
                "The river Bazga is a tributary of the Bohotin River in Romania ."
            ]
        },
        {
            "input": "结论是，我们都是一个神圣心灵的完美精神思想，并且表现出精神，而不是物质身体。",
            "output": [
                "The conclusions are that we are all perfect spiritual notions of one divine spirit and manifest the spirit , not a material body ."
            ]
        }
    ],
    "Instruction_language": [
        "English"
    ]
}