{
    "Contributors": [
        "Ishani Mondal"
    ],
    "Source": [
        "broad_twitter_corpus"
    ],
    "URL": [
        "https://github.com/juand-r/entity-recognition-datasets/tree/master/data/BTC"
    ],
    "Categories": [
        "Named Entity Recognition"
    ],
    "Reasoning": [],
    "Definition": [
        "In this task, you are given a sentence. You are expected to recognize the name of company or organization. Although there might be several correct answers, you need to write one of them."
    ],
    "Input_language": [
        "English"
    ],
    "Output_language": [
        "English"
    ],
    "Instruction_language": [
        "English"
    ],
    "Domains": [
        "Commonsense -> Concepts and Relations -> Social Commonsense",
        "Professions",
        "Social Media -> Twitter"
    ],
    "Positive Examples": [
        {
            "input": "I want to work dedicatedly for Microsoft Corporation",
            "output": "Microsoft Corporation",
            "explanation": "Microsoft Corporation is a multi-national corporate organization where people do professional work. Hence it should be tagged as organization."
        },
        {
            "input": "Hyland provides a lot of perks to its employees",
            "output": "Hyland",
            "explanation": "Hyland Corporation is a multi-national corporate organization where people do professional work. Hence it should be tagged as organization."
        }
    ],
    "Negative Examples": [
        {
            "input": "She works as a waitress.",
            "output": "waitress",
            "explanation": "Here waitress is a profession and not an organization. Hence, it should not be tagged."
        },
        {
            "input": "JW Marriott is one of the best 5-star hotels in this city.",
            "output": "5-star hotels",
            "explanation": "5-star hotels is a rating of the hotel and not an organization. Hence, it should not be tagged so."
        }
    ],
    "Instances": [
        {
            "id": "task1479-d6d4051091cd43618c3ea656417b4b1a",
            "input": " I 'll be interviewed by Fran Kelly on ABC Insiders shortly #auspol",
            "output": [
                "ABC Insiders"
            ]
        },
        {
            "id": "task1479-f2f4446aa81d41f38f970c41e79ad155",
            "input": " #WestConnex costruction will accelerate following agreement signed by C ' wlth and NSW Govts http://t.co/g347msss78 http://t.co/ihcEFgQCmb",
            "output": [
                "C ' wlth"
            ]
        },
        {
            "id": "task1479-b8053f6365b646639219486d3a392de9",
            "input": " BREAKING NEWS ; Malaysian passenger airliner crashes in Ukraine . [ Pic from Aljazeera live TV ] . #MH17 http://t.co/uoCBsfayWx",
            "output": [
                "Aljazeera live TV"
            ]
        },
        {
            "id": "task1479-bf528724978242efbdab03ef01f7f5dd",
            "input": " Sad to learn that Past Times on Palmerston Road is closing # Southsea RT kimberleybarber http://t.co/tvbtAtAk",
            "output": [
                "Past Times"
            ]
        },
        {
            "id": "task1479-c830c6003041447298a65a7cbea7446b",
            "input": " @ TottenhamTories I was thinking of you guys when I posted it ! Tottenham Tories got me involved with Polish community !",
            "output": [
                "Tottenham Tories"
            ]
        },
        {
            "id": "task1479-8d937d792009476280c6b9eae738f512",
            "input": " Nigeria : Super Eagles Have Everything to Play for http://t.co/BhQeqZjVO8 #WorldCup",
            "output": [
                "Super Eagles"
            ]
        },
        {
            "id": "task1479-e4fcdfe6f12747a89a4fe4a27a878027",
            "input": " #nigeria Inyama Reassures Nigerians Over Super Eagles ' Commitment : http://t.co/r0GEWh8IwE",
            "output": [
                "Super Eagles"
            ]
        },
        {
            "id": "task1479-57d2ccaf45bd4d6585a37c0d47326e00",
            "input": " Today 's Olympics-wheels-coming-off story : London 2012 : Olympic watchdog member quits over Dow links http://t.co/RNXZ8tmR",
            "output": [
                "Olympic watchdog"
            ]
        },
        {
            "id": "task1479-b789b62c995544a883777fd707533af0",
            "input": " Cutie special edition #LittleMachines only avails at Walmart Canada ! Cool bag included ! I want it . http://t.co/KUGcD3zkZv",
            "output": [
                "Walmart Canada"
            ]
        },
        {
            "id": "task1479-6e10890952944817bf44ec3249cbef3e",
            "input": " RT SoibiTonteLJ : Smh at Big Brother . Its really downgraded over the years . « « Its on channel 5 mate ! Ofc it has",
            "output": [
                "channel 5"
            ]
        },
        {
            "id": "task1479-a345198d87b944a7906b5cbc4f3feb77",
            "input": " # JEDWARDCelebWeddingChannel 5 thats well getting watched ; ) !",
            "output": [
                "channel 5"
            ]
        },
        {
            "id": "task1479-51aa2ea2cddd40b3bb1db878c69ff9f9",
            "input": " U . S . to reveal intelligence today that supports claims that missile that downed #MH17 came from separatist-controlled area : State Dept .",
            "output": [
                "State Dept"
            ]
        },
        {
            "id": "task1479-1a103b91967f4640aacc3da53801b03c",
            "input": " #mirror article attacking me re #housingbenefit is wrong . West Berks Council say their figures ' over estimated by significant amount '",
            "output": [
                "West Berks Council"
            ]
        },
        {
            "id": "task1479-0c59659e9ea442cbb31bc286e6648682",
            "input": " http://t.co/gXUIAlgw is running a competition where you could win 8 tickets to the Super Bowl SuperBash at the o2 Arena . Head over .",
            "output": [
                "Super Bowl"
            ]
        },
        {
            "id": "task1479-ddd9b1e0bdf244cda0c9d18fac59a0d2",
            "input": " I salute Eastwood Fire Brigade on 100 years ' serving our community #auspol #bennelong http://t.co/rxBxseBH9g",
            "output": [
                "Eastwood Fire Brigade"
            ]
        },
        {
            "id": "task1479-05ce8556583c4e0d80cb018a16430831",
            "input": " One year after 28 Sun- Times photojournalists were laid off , where are they now ? http://t.co/GTf6RrcZ8Q ( via @ poynter )",
            "output": [
                "Sun- Times"
            ]
        },
        {
            "id": "task1479-62e27795154f4253b32d1bff2c878d60",
            "input": " Latest : Alliance Party Offices in East Belfast attacked again http://t.co/IlxXyE9xBA",
            "output": [
                "Alliance Party"
            ]
        },
        {
            "id": "task1479-a634e1c9c1a54f8dac5d3b14b1f3fc0e",
            "input": " Info for Potential NASW Board Candidates : Interested in running for the NASW board or just want to know how the . . . http://t.co/mYCkITtIIp",
            "output": [
                "NASW Board"
            ]
        },
        {
            "id": "task1479-c208c27b3d4749bc8526c52a382a8e5f",
            "input": " Welcome to Manchester United @ juanmata10",
            "output": [
                "Manchester United"
            ]
        },
        {
            "id": "task1479-22ce86811c684d778c43dbb8276cf8ec",
            "input": " I 'm at Caffè Nero ( 21 High St . , Bath ) http://t.co/IkncHGtI",
            "output": [
                "Caffè Nero"
            ]
        },
        {
            "id": "task1479-6fb61c3c95ed4aa39fe01069b7e55ad4",
            "input": " Great piece by Christine Milne in today 's Mercury . People need to realise that the Liberal party plan to log . . . http://t.co/NRcHJlcvs1",
            "output": [
                "the Liberal party"
            ]
        },
        {
            "id": "task1479-71580e7a75b441c69a4bdeeacc5d04bc",
            "input": " People mourn #MH17 in front of the Netherlands Embassy . The day in photos : http://t.co/wRGNmgNE1J ( AFP / Getty Images ) http://t.co/gGqBNl0P52",
            "output": [
                "Getty Images"
            ]
        },
        {
            "id": "task1479-15cf729eb2e74ee8b4228eab809c321f",
            "input": " Countdown to World Press Freedom Day 2014 : IFJJ Appeals for Re- Opening of Iranian Union Offices http://t.co/xVeCiDRRCy #PressFreedom",
            "output": [
                "World Press"
            ]
        },
        {
            "id": "task1479-bf2fbaa53ce84b9e81578513f7048bc6",
            "input": " Photo from @MatevzNovak appears to show wreckage from Flight #MH17 in Ukraine http://t.co/0c5SaansoX",
            "output": [
                "#MH17 in Ukraine"
            ]
        },
        {
            "id": "task1479-ed3cd4dc14854b51a1d0adff17856d7b",
            "input": " I used to be so bad at naming any k idol group members pmsl I would get so confused and now I 'm pro ; ) ) )",
            "output": [
                "k idol"
            ]
        },
        {
            "id": "task1479-03fdeb655d264f55bb2875ced8ed4c1d",
            "input": " Today 's disappointment : Black Sheep '\"' Golden Sheep '\"' Pale Ale .",
            "output": [
                "Black Sheep"
            ]
        },
        {
            "id": "task1479-678de8316653482cb08bae7411bbabb7",
            "input": " NY Times profile of possibly the most unbearable couple ever : Wonderfully cringe http://t.co/HtxkjYFQpG",
            "output": [
                "NY Times"
            ]
        },
        {
            "id": "task1479-765534e62d8c4877b2ce7766bb2ecc1c",
            "input": " AAN and 41 Free Speech , Open Government and Public Interest Groups Urge the FCC to Protect Net Neutrality http://t.co/KTyJcrqskO",
            "output": [
                "41 Free Speech"
            ]
        },
        {
            "id": "task1479-62fde64fad824b75901817098f3acd98",
            "input": " @ Tod123x @ JewishNewsUK Please don ’ t confuse Jews with the actions of the Israeli government .",
            "output": [
                "Israeli government"
            ]
        },
        {
            "id": "task1479-f71be0e5f32642dd9fee43b3202e48fa",
            "input": " BBC News - Symantec advises disabling pcAnywhere software http://t.co/Ae7psUQn - - Oops . I wo n't trust them again .",
            "output": [
                "BBC News"
            ]
        },
        {
            "id": "task1479-a33bb9fcc0b147f8babe2d2fa4b8b07c",
            "input": " BBC News - Hong Kong firm MTR wins £ 1 . 4bn Crossrail franchise http://t.co/27lww23S9P",
            "output": [
                "BBC News"
            ]
        },
        {
            "id": "task1479-99d1983b5ea14d57ac09e7f500c7014a",
            "input": " Russia Today shares this photo that reportedly shows debris of the #MH17 flight on the Russia Ukraine border http://t.co/bGWI4eO4CH",
            "output": [
                "shares this"
            ]
        },
        {
            "id": "task1479-0b434d88c047437d99a146595f77f0b9",
            "input": " How stunning is my sister ? ! ? Fashion credits : Kardashian Kollection pants , Saint Laurent blouse , … http://t.co/bTUPqJ9uju",
            "output": [
                "Saint Laurent"
            ]
        },
        {
            "id": "task1479-e010103d67ef409ebbc6237433419de3",
            "input": " Alert : Victoria St Hamilton - Hamilton Police have attended a business in Victoria Street Hamilton after a memb . . . http://t.co/BynJmHQkYD",
            "output": [
                "Hamilton Police"
            ]
        },
        {
            "id": "task1479-54b8b07d82e842f28cf956a6dc1d7162",
            "input": " Arrest following attack at Waikato University - Today Hamilton Police arrested an 18 year-old Hamilton man in rela . . . http://t.co/85yRXyLp12",
            "output": [
                "Hamilton Police"
            ]
        },
        {
            "id": "task1479-fe8a9930c58546c4b71b94962a8f1d1e",
            "input": " Eamon Gilmore congratulates Joan Burton , the new Labour Party leader . \" It 's a tough job . I know ! \"",
            "output": [
                "Labour Party"
            ]
        },
        {
            "id": "task1479-dbb97ccd2d7c44e39f35b96c5b1591bf",
            "input": " Orpington Jobs : Store Manager / General Manager : Randstad Employment Bureau - Retail Sales - . . . http://t.co/7iNdrLTT # Jobs # Orpington",
            "output": [
                "Randstad Employment Bureau"
            ]
        },
        {
            "id": "task1479-aaa1855352bc499bb04a0ca54a7dff48",
            "input": " East Ukraine rebels leader Borodai blames Ukraine army for #MH17 crash . ' We do n't have weapon like that ' , he tweets https://t.co/8olLIWkZnx",
            "output": [
                "Ukraine army"
            ]
        },
        {
            "id": "task1479-88bb4b8837bc4216afecb910748b9776",
            "input": " My grandson Mikey . First in the queue for the opening ceremony at the Special Olympics in Limerick http://t.co/V8e57ZECTa",
            "output": [
                "Special Olympics"
            ]
        },
        {
            "id": "task1479-c942493a9ef349b295eebc3e66145b8e",
            "input": " @ 27KHV @ sikorskiradek @ olacicho And that 's a fair point ( though no one said I worked with ' Fox News ' , it was a tad more serious ) .",
            "output": [
                "Fox News"
            ]
        },
        {
            "id": "task1479-8dafdab4e4ba49539fbaf42a9db84426",
            "input": " WOW ! Just been overtaken by a MV Augusta Brutale what a machine ! Someone has taste and some Hot wheels .",
            "output": [
                "MV Augusta"
            ]
        },
        {
            "id": "task1479-ee03ab0e2091419aa7cf45968f1abde9",
            "input": " Tonight on Anger Management Toronto Blue Jay 's pitcher Conner Greene . . ! Tune in to #FX at 9 . . ! … http://t.co/N3Jxw9gOwM",
            "output": [
                "Toronto Blue Jay"
            ]
        },
        {
            "id": "task1479-a7cf5a77bcb6415181bdd28f02bf8043",
            "input": " 20th call for transparency on use of #drones comes today from #UN Secretary- General . Timeline http://t.co/UoRjQOfFCN http://t.co/rVca8dVLba",
            "output": [
                "#UN Secretary- General"
            ]
        },
        {
            "id": "task1479-7e14787ea870450085d0ad0aef0c9b48",
            "input": " Dominos pizza delivery guy dropping off pizzas at a Chinese restaurant . Classic . http://t.co/fvEE8Z2CDx",
            "output": [
                "Dominos pizza"
            ]
        },
        {
            "id": "task1479-b917ebcace8d46db9527f37298004ff6",
            "input": " When Man City need to score and teams sit very deep against them and get everyone behind the ball they really do n't look like scoring .",
            "output": [
                "Man City"
            ]
        },
        {
            "id": "task1479-d12ca8a7822b4ed48ec5d7e3e953d944",
            "input": " Man City XI : Hart , Zabaleta , Kompany Demichelis , Kolarov , Garcia , Yaya Toure , Milner , Silva , Nasri , Dzeko",
            "output": [
                "Man City"
            ]
        },
        {
            "id": "task1479-80c32b6153254ec986682abfb07d1c89",
            "input": " # HackneyCouncil Labour councillors making a meal of Ken 's fares policy - despite everyone knowing it does n't add up . Get real , guys !",
            "output": [
                "HackneyCouncil Labour"
            ]
        },
        {
            "id": "task1479-589f128aab59445f88e28bb956e7591a",
            "input": " Shock Cuts to local mental health services in the Rudd Government 's 2010 Budget . Under the Better Access . . . http://bit.ly/bAQgme",
            "output": [
                "Rudd Government"
            ]
        },
        {
            "id": "task1479-149fab346e994150aa0e39a925a540d4",
            "input": " I met w / Wavepark Group today who are proposing a WA surfing park . No sharks and plenty of waves for pros & beginners http://t.co/qeCl9puKue",
            "output": [
                "Wavepark Group"
            ]
        },
        {
            "id": "task1479-f891396c1bc94c6a9ba5620075d6cc79",
            "input": " Wow ! ! Our @thek_kollection at @ lipsylondon was voted Best Celeb Designer Collection by Reveal Magazine … http://t.co/j0KUEQ4cdQ",
            "output": [
                "Reveal Magazine"
            ]
        },
        {
            "id": "task1479-8dc81fe1c38a47f2b6de8fc06ba02058",
            "input": " My work for missmillco and Lucy in Disguise http://t.co/D7if6Eig",
            "output": [
                "Lucy in Disguise"
            ]
        },
        {
            "id": "task1479-302c76123a6149d59f22aef3b5cd0e18",
            "input": " Track me from link on FB #co54 #colorado54 #14ers #colorado14ers #secondmilewater #co54pilgrimage http://t.co/Ew5ovI90ht",
            "output": [
                "#14ers #colorado14ers"
            ]
        },
        {
            "id": "task1479-d7238c295b6846fabd7931a908778693",
            "input": " Australia Post currently appearing before Senate inquiry",
            "output": [
                "Australia Post"
            ]
        },
        {
            "id": "task1479-bc0760078ba848bf98981c1d4f2c0627",
            "input": " According to the Beeb , there 's talk of Pienaar going back to Everton . Defoe allegedly in Liverpool , remember . Whole thing odd ( JamesMawFFT )",
            "output": [
                "the Beeb"
            ]
        },
        {
            "id": "task1479-8378ba7587b8418689e2e676933a3f18",
            "input": " Surprised that AlSharqiya TV has put on qussat arba ' eeniyat Imam AlHussain ( as ) ! Masha ' Allah .",
            "output": [
                "AlSharqiya TV"
            ]
        },
        {
            "id": "task1479-445672c4cd7f45fda082d7ffb6460d5c",
            "input": " Ukraine Officials claim to have data of call between Pro Russian separatists and a Russian Intel Officer before taking the plane down #MH17",
            "output": [
                "Pro Russian separatists"
            ]
        },
        {
            "id": "task1479-c5c7b60855df45f499100e19c9ec488d",
            "input": " ACT marriage bill to be challenged in High Court http://t.co/ixaV5qD8Ws via @audioboo",
            "output": [
                "High Court"
            ]
        },
        {
            "id": "task1479-13e626cad2f0478c90595d6df738de51",
            "input": " Rupert Murdoch 's $ 80bn bid for Time Warner is just the opening gambit http://t.co/I5xIxjp63G",
            "output": [
                "Time Warner"
            ]
        },
        {
            "id": "task1479-9de1578733774250a54cda9b70483fb9",
            "input": " Marcus Collins to cover White Stripes - Seven Nation Army ? Personally i think it will be good , whats everyone else think ",
            "output": [
                "?White Stripes"
            ]
        },
        {
            "id": "task1479-186fdeb1fa5a459bb949f89bd872aadd",
            "input": " Stock clearance deal - Mamas & Papas Trip Buggy ( brand new - just out of the box ) in Apple Green , including Mix . . . http://t.co/jBEudtAD",
            "output": [
                "Mamas & Papas"
            ]
        },
        {
            "id": "task1479-f7a0cf370ab646209ac7ae54c3ec4457",
            "input": " Watch astro awani . it 's comfirmed . Just not yet confirm if it 's being shot down , related to the heavy fighting between russia & ukraine #mh17",
            "output": [
                "astro awani"
            ]
        },
        {
            "id": "task1479-c2e10c07dadf401d96c43986679f0599",
            "input": " The FA commission has , after months of brainstorming , come up with the master plan of a B team league . . . . As you were .",
            "output": [
                "FA commission"
            ]
        },
        {
            "id": "task1479-49af396990df4c0598f6e75d44163346",
            "input": " There 's @ AudreyCarville signing off on Morning Ireland . She will be hosting the Amnesty hour in MindField at #ElectricPicnic2014 6pm today",
            "output": [
                "Morning Ireland"
            ]
        },
        {
            "id": "task1479-4cd725da3ec74b94bbefa9e0af53ecd7",
            "input": " #KKTeam Quem foi o adversário do Milan na estreia de Kaká pelo Campeonato Italiano , em 2003 ? A . Napoli ; B . Ancona ; C . Genoa #KKQuiz",
            "output": [
                "Campeonato Italiano"
            ]
        },
        {
            "id": "task1479-bb7be9a293fe481eb80299217f2b547a",
            "input": " I can not believe that Jesse Ventura successfully sued the widow of a fallen Navy SEAL . Has he no shame ",
            "output": [
                "?Navy SEAL"
            ]
        },
        {
            "id": "task1479-40e0f270c2674b25b1f4bf5ad7ceecdf",
            "input": " Photo : Oh , Australian Copyright Council , you assonant scallywags . http://t.co/WGGUAqjCoT",
            "output": [
                "Australian Copyright Council"
            ]
        },
        {
            "id": "task1479-576ca797f48947ffab4356db9341e9bc",
            "input": " Ukraine govt advisor says nearly 300 killed on plane that might be #MH17, says jet was shot down by separatists : Interfax",
            "output": [
                "Ukraine govt"
            ]
        },
        {
            "id": "task1479-739d87ca621a4883adcf4cb0e1acc71e",
            "input": " How and why the Financial Times built a digital FT Weekend ( @ JaspJackson via @ mediabrief ) http://t.co/72avc6DrfU #MustReads",
            "output": [
                "Financial Times"
            ]
        },
        {
            "id": "task1479-c8b381d7df884105a855c426a250c4ed",
            "input": " DISGRACE : An Atalanta fan not only threw a banana at AC Milan 's Kevin Constant … but also a knife ! ! http://t.co/KXogzwQNu1",
            "output": [
                "AC Milan"
            ]
        },
        {
            "id": "task1479-21162116efc8488fa495fa7b80f973a3",
            "input": " Team USA making us proud ! Ca n't wait to catch my boy @ stevenlangton and his team go for the Gold this weekend @ usolympic #GoTeamUSA",
            "output": [
                "Team USA"
            ]
        },
        {
            "id": "task1479-d47908f899a94905bb75f28a9f98adc1",
            "input": " just finished newsradio with marius , about to talk to abc news breakfast then sky am agenda .",
            "output": [
                "abc news"
            ]
        },
        {
            "id": "task1479-d82bce0499fc4a7c8467d808d762e391",
            "input": " Hey girl , the Bottle Boys have a favor to ask . http://t.co/n5r4dAWjm6 http://t.co/pT1xLUnrmG",
            "output": [
                "Bottle Boys"
            ]
        },
        {
            "id": "task1479-3018611fa36b426b9877783be7b7d719",
            "input": " 72 % Off at Serenity Hair Spa http://t.co/WzvKXeZ8",
            "output": [
                "Serenity Hair Spa"
            ]
        },
        {
            "id": "task1479-f4e319b9070e44e69729c7999e325a3a",
            "input": " Celebrating 1000 members at Somerton SLSC- first club in SA to achieve this . @ Somerton Surf Life … http://t.co/dyB6wKUevf",
            "output": [
                "Somerton SLSC-"
            ]
        },
        {
            "id": "task1479-f739a7492fd24996af99acc759f62924",
            "input": " Really enjoyed the United Charities Market in Biddulph this morning",
            "output": [
                "United Charities Market"
            ]
        },
        {
            "id": "task1479-5329dd84aff74822947d1ec2d60c4d39",
            "input": " #MH17: New York Times praises PM Najib for brokering deal to recover black boxes , remains of victims and secure safe access to crash site",
            "output": [
                "New York Times"
            ]
        },
        {
            "id": "task1479-506e9d31c10346b69118c1fdd0b9f363",
            "input": " Interesting opinion piece in the New York Times . Ca n't wait to hear what the perpetually outraged have to say . http://t.co/1GbFYFCKs3",
            "output": [
                "New York Times"
            ]
        },
        {
            "id": "task1479-08f2222697664902aa9dc02ee32fb578",
            "input": " Internal innovation report says the New York Times needs to up its digital game or else — Tech News and Analysis - http://t.co/X61FknHKH3",
            "output": [
                "New York Times"
            ]
        },
        {
            "id": "task1479-2a0f39a44c8847d4a78366afd42e089f",
            "input": " @ y_alibhai I get my fair share of visits through Justice Select Committee . . . . #KeepIngInTouch",
            "output": [
                "Justice Select Committee"
            ]
        },
        {
            "id": "task1479-45831ebd55cd4e6f81c2ea811a7b5861",
            "input": " Why 've I only just discovered The Vaccines ? Great debut album .",
            "output": [
                "The Vaccines"
            ]
        },
        {
            "id": "task1479-99dbbf84fa9a470da56a0b500666682f",
            "input": " HTFPNewsinBrief Local World aims for ‘ world class mobile product ’ : Company announces new digital product director http://t.co/yUA7Q9hnLJ",
            "output": [
                "HTFPNewsinBrief Local World"
            ]
        },
        {
            "id": "task1479-315c52dd040b4a058b7001e828cce4a7",
            "input": " Is that Dana 's brother , John Brown , who is now suing IN & M , fortnight after Dana herself initiated proceedings ",
            "output": [
                "?IN & M"
            ]
        },
        {
            "id": "task1479-447263a291664f28afce2982b19320d6",
            "input": " CPA Australia says ASIC is a damaged brand in the marketplace",
            "output": [
                "CPA Australia"
            ]
        },
        {
            "id": "task1479-1062d0fa9d364a2ea959d3a370d829dd",
            "input": " Ca n't help but think of the times I 've had with you , pictures and some memories will have to help me through . # nowplaying Dear God- A 7x & lt ; 3",
            "output": [
                "The Times"
            ]
        },
        {
            "id": "task1479-95ddf48c600042b09962a95d28b9338f",
            "input": " Thanks to tchesshyre for his article on Djerba , Tunisia , in The Times - http://t.co/eQkCRySp via AddThis . Spicy octopus for tea anyone ",
            "output": [
                "?The Times"
            ]
        },
        {
            "id": "task1479-437752ee326d4a81a15642018f6f51ef",
            "input": " And move with the times . Movie and book publication much the same . Anyway , rant over !",
            "output": [
                "The Times"
            ]
        },
        {
            "id": "task1479-9a0f804ab8fd4ed7941540467cd51c39",
            "input": " @ Mayorjd It is important infrastructure for our region and indeed regional Australia , here it is our Casino Saleyards and Grafton airport",
            "output": [
                "Casino Saleyards"
            ]
        },
        {
            "id": "task1479-489b415ccbb0468c98c1da076c4114ca",
            "input": " Michael Niziolek ( @ michaelniziolek ) is covering sports for Ann Arbor News and MLive",
            "output": [
                "Ann Arbor News"
            ]
        },
        {
            "id": "task1479-4cb6081185b8401ba11c8c9e1eed0943",
            "input": " Air India reroutes flights to avoid Ukrainian airspace : Civil Aviation Ministry #MH17",
            "output": [
                "Air India"
            ]
        },
        {
            "id": "task1479-a1bac40c8a9c4d6cb3679786906a7a6b",
            "input": " Birmingham City : Will Colin Doyle stay or go ? http://t.co/x3qTmOw7 # bcfc # birminghamcity # blues # standrews # keeprighton # colindoyle # goalie",
            "output": [
                "Birmingham City"
            ]
        },
        {
            "id": "task1479-b68f8e3925be42bb934286d3e71f9f01",
            "input": " Riot Games Sydney Office ! http://t.co/DZ0SUuUD65 jobs for community and esports ! How big will the Sydney team be @riotpendragon ",
            "output": [
                "?Riot Games"
            ]
        },
        {
            "id": "task1479-a64d65ec38e54687a6626b66aaef8d57",
            "input": " It 's happened again . One Direction have come on Spotify & I 've not switched it over . You may form an orderly queue and shoot me accordingly .",
            "output": [
                "One Direction"
            ]
        },
        {
            "id": "task1479-883160cbf7004265874587bdd787e878",
            "input": " Can not believe how many young girls there were queuing outside the Brighton Centre for One Direction : /",
            "output": [
                "One Direction"
            ]
        },
        {
            "id": "task1479-957f9adbed3d435aa41338896cb49d13",
            "input": " Very happy to be back on the UK show this year . The last year I was on it we found One Direction , Rebecca Ferguson , Cher and Matt Cardle",
            "output": [
                "One Direction"
            ]
        },
        {
            "id": "task1479-f990dcab83af4dee92b00a35bab4c458",
            "input": " Heard the latest Hack Report podcast yet ? How to write a news story , diversity in #radio, and youth #media: http://t.co/yMMi5LC1RE ( 8mins )",
            "output": [
                "Hack Report"
            ]
        },
        {
            "id": "task1479-f6bede3a32b940349c2dacee0ff2b77e",
            "input": " Colwyn Bay 6th in prem league , just qualified for CL knockout stages , and im losing dressing room for '\"' underachieving '\"' ! ! # fm 12 # unbelievable",
            "output": [
                "Colwyn Bay"
            ]
        },
        {
            "id": "task1479-5374082b6b624b0ca65073f04e9ea669",
            "input": " Colwyn Bay Civic Society writing to @ ConwyCBC re @ PorthEirias",
            "output": [
                "Colwyn Bay"
            ]
        },
        {
            "id": "task1479-680f13ae087c4ee590c521ab87345699",
            "input": " Boulder Weekly wins 36 awards in Top of the Rockies contest , Westword editor Patty Calhoun recognized http://t.co/Ggh5UVzoh7",
            "output": [
                "Boulder Weekly"
            ]
        },
        {
            "id": "task1479-b5aa7e1c5d0c4afabec563396a7b031f",
            "input": " This public enemies thing on BBC 1 is weird .",
            "output": [
                "BBC 1"
            ]
        },
        {
            "id": "task1479-fa75d33bd62f4da598684396e13912d2",
            "input": " Why is there World War 1 porn on BBC 1",
            "output": [
                "BBC 1"
            ]
        },
        {
            "id": "task1479-121da61977484770972112fd40f9c54d",
            "input": " Colleague watching Death Row Dogs on BBC 1 - not sure about the animals but the owners should certainly be muzzled .",
            "output": [
                "BBC 1"
            ]
        },
        {
            "id": "task1479-bf48b16655754917927f83964ad3e21e",
            "input": " Also Noah and the Whale sound like Tom Petty 's had a stroke and is determined to cover a load of Deacon Blue songs .",
            "output": [
                "Deacon Blue"
            ]
        },
        {
            "id": "task1479-37ed8faeff9349fab81a5c9cc69f2c5b",
            "input": " Malaysian Airline #MH17 shot down by russian missiles . How do you mistake an airliner for a fighter jet ? #PrayForMH17",
            "output": [
                "Malaysian Airline"
            ]
        },
        {
            "id": "task1479-8d4c5450e9774706a870686ba974b309",
            "input": " The Japanese whaling is illegal and immoral . The Australian Government has failed utterly to stop the Japanese . . . http://t.co/1tpNVsAfUs",
            "output": [
                "Australian Government"
            ]
        },
        {
            "id": "task1479-a936ac65fbcc43328606d905ef745d20",
            "input": " Hanging with officialdfoster at erase ms gala http://t.co/HQoh0DPgjb",
            "output": [
                "erase ms gala"
            ]
        },
        {
            "id": "task1479-27b60fa160c04bda867ec94040fbdeb1",
            "input": " Martin facing split in FF as TDs urge deal with Sinn Fein http://t.co/p4IBM4klke via @ Independent_ie Why is this even a story this far out ",
            "output": [
                "?Sinn Fein"
            ]
        },
        {
            "id": "task1479-2592df5e557f493887123a45eea97f44",
            "input": " February 2001 issue of \" The Fenian \" newsletter of Sinn Fein Dublin South West http://t.co/18dTgYUhXa",
            "output": [
                "Sinn Fein"
            ]
        },
        {
            "id": "task1479-3088f5bd11ac4f7a87be5b323aa13085",
            "input": " Trailer | Upper Middle Bogan | Premieres Thursday 15 August ABC 1 http://t.co/ecuou4ax6i",
            "output": [
                "ABC 1"
            ]
        },
        {
            "id": "task1479-28f305d6b9ea4f5ca966ec461ae1744c",
            "input": " And now , batting for the Detroit Tigers . . . http://t.co/OpgQJ62OYH",
            "output": [
                "Detroit Tigers"
            ]
        },
        {
            "id": "task1479-d456dad3043b4b1db79539155945ef38",
            "input": " And this one too @ rivadanetworks Rivada Research patents list ( updated weekly ) http://t.co/6J38CJv3Oq",
            "output": [
                "Rivada Research"
            ]
        },
        {
            "id": "task1479-ce6c692e574d4779b3bbf80f23443269",
            "input": " The first showing of the Modern Slavery campaign ad will be at 18 : 42 today on Channel 4 . Great response to the campaign so far .",
            "output": [
                "Channel 4"
            ]
        },
        {
            "id": "task1479-2e52b4944b214d6fbef7566f03c38124",
            "input": " Our Leicester City expert 's verdict on their key players and prospects in the Premier League next season http://t.co/AESTCNs9xz #ffscomm",
            "output": [
                "Premier League"
            ]
        },
        {
            "id": "task1479-2c73ce31426342f485f039a20347a634",
            "input": " Are you a visual communicator looking for some inspiration & mind-blowing ideas ? RSVP now for See Change ! May 13 - 14 . http://t.co/HnCw3W13ld",
            "output": [
                "See Change"
            ]
        },
        {
            "id": "task1479-22018a5108f24ac1aba120bad40b4097",
            "input": " ' We are Sex Bob- Omb & were here to make you think about death & get sad & stuff ! ! ' # scottpilgrim",
            "output": [
                "Sex Bob- Omb"
            ]
        },
        {
            "id": "task1479-00cb5770e5e144e793e07df337570b22",
            "input": " 1st task post election : opening Dromana Bowls club season 2013 : 14 . Little country booths y ' da are a reminder that we find Oz in the local .",
            "output": [
                "Dromana Bowls club"
            ]
        },
        {
            "id": "task1479-f550b6c0551e4af0bbc9192442c0d42f",
            "input": " Partizan Belgrade v Tottenham : Player ratings http://t.co/7U66O3cWm0 http://t.co/EqzOx6Ww4Q",
            "output": [
                "Partizan Belgrade"
            ]
        },
        {
            "id": "task1479-a044c12016b74d8eb813f2d895c88108",
            "input": " What 's the real meaning of the G-Cloud ? | BusinessCloud 9 : http://t.co/gi2Pbouz via AddThis",
            "output": [
                "BusinessCloud 9"
            ]
        },
        {
            "id": "task1479-ede9576015b0468ea3f8b237134d74cd",
            "input": " Current state of play of by-election candidate list ahead of tonight 's Fianna Fail Roscommon- South Leitrim convention http://t.co/3nF5Hmb8S4",
            "output": [
                "Fianna Fail"
            ]
        },
        {
            "id": "task1479-5bb1644d395a40b186ee2c69d68e70c4",
            "input": " # moviethingstodobeforeidie go to the quidditch world cup # nerdtweet",
            "output": [
                "World Cup"
            ]
        },
        {
            "id": "task1479-0fee44c0ba0548559ca5cc23525869d2",
            "input": " 10 Things You Should Know Heading Into The @ FIBA Basketball World Cup Round of 16 ( via http://t.co/K4phvCviyi): http://t.co/b5OdCoRlpt",
            "output": [
                "World Cup"
            ]
        },
        {
            "id": "task1479-5da4334a95c04301ae19ca1228c42b78",
            "input": " The last time @ USSoccer played Portugal in the World Cup , this happened . http://t.co/l0Oioraddi",
            "output": [
                "World Cup"
            ]
        },
        {
            "id": "task1479-e6f7b32f2ec5451fb3041186ac504306",
            "input": " The last time Honduras scored a World Cup goal , “ Eye of the Tiger ” was one of the top songs on the charts . # 1982",
            "output": [
                "World Cup"
            ]
        },
        {
            "id": "task1479-2b8b052fb96048898b0d01592340c88a",
            "input": " I am looking forward to this mind-controlled robot exoskeleton ( controlled by a paralyzed boy ) at the World Cup opening .",
            "output": [
                "World Cup"
            ]
        },
        {
            "id": "task1479-ce92a825654044ceb7b71f525f89ecf5",
            "input": " What do you think of Roy Hodgson 's @ England squad for the 2014 FIFA World Cup in Brazil ? #3Lions http://t.co/kGAxVYn1xi #ffscomm",
            "output": [
                "World Cup"
            ]
        },
        {
            "id": "task1479-9226458214f6404f93fb23b1cf2efdce",
            "input": " Hallam FM sources say Doncaster striker Billy Sharp is undergoing a medical with Southampton ahead of a possible move . # hallamtransfers",
            "output": [
                "Hallam FM"
            ]
        },
        {
            "id": "task1479-a8ced3f005dd4c9eba5fe165e5684877",
            "input": " # Twitition Bring 1 DToDenver http://t.co/KXSrJeLh",
            "output": [
                "1 D"
            ]
        },
        {
            "id": "task1479-c890e65729de4663aca4d971fe425d8a",
            "input": " # directioners Follow Backk ? ♥ # 1 Dfamily",
            "output": [
                "1 D"
            ]
        },
        {
            "id": "task1479-bd09b2ef392c4b97981d9e8ab38d7fd6",
            "input": " Looking for a model for a 1 day shoot . FM 30 ' ish , easy in front of a camera , size 12 . Modelling vintage clothes for new website . Contact me .",
            "output": [
                "1 D"
            ]
        },
        {
            "id": "task1479-f6aaa8370b064d6a9f787a15497a6d3f",
            "input": " USA ! Tune in to @ GMA tomorrow morning for an exclusive sneak peek at 1 D ’ s \" You and I ” video ! #YouAndIonGMA 1 D HQ x",
            "output": [
                "1 D"
            ]
        },
        {
            "id": "task1479-5f8ea55b9c16428cae3e2ccdc332012f",
            "input": " Do you want access to #YouAndI stems to remix the track ? Check this out . . . 1 DHQ x http://t.co/CmxbxKYcxe",
            "output": [
                "1 D"
            ]
        },
        {
            "id": "task1479-840f48754b124ff3a797b525fd394e66",
            "input": " USA ! 1 D are up for 3 @ radiodisney #RDMAS! Tune in to the show tonight at 8 / 7c on @disneychannel ! 1 DHQ x",
            "output": [
                "1 D"
            ]
        },
        {
            "id": "task1479-6c2b4262bae6497fa8be61f9adbb4bae",
            "input": " Every week for the next 5 weeks we 'll be surprising 5 newsletter subscribers with a pair of 1 D shoes . . . http://t.co/REhgxv0y6F",
            "output": [
                "1 D"
            ]
        },
        {
            "id": "task1479-d57c81371db04ebcb15f1dbfc2cc54f3",
            "input": " @ DeclanHarmon @ RTERadio1 Declan , there will not be anything bad said about the fantastic , amazing Professor . Go into the bold corner .",
            "output": [
                "1 D"
            ]
        },
        {
            "id": "task1479-a27f1047464046589032773e82748171",
            "input": " Let 's ask : increase Irish corp tax to a standard EU rate in exchange for 1 : 1 drop income tax load ? MT @ EamonDelaney10 : #Picketty",
            "output": [
                "1 D"
            ]
        },
        {
            "id": "task1479-531ede9d1ea84a6c87e790519d1051dc",
            "input": " Was your area Pro- Treaty or Anti- Treaty ? The 1921 Dáil vote on the Anglo- Irish Treaty , in map form : http://t.co/RHn1kb2g2d",
            "output": [
                "1 D"
            ]
        },
        {
            "id": "task1479-0a6a55e66fcc47b1b7c75a0e07480d41",
            "input": " Imagine you went onto the Sponsor A Dog website and your Mum was on the first page .",
            "output": [
                "Sponsor A Dog"
            ]
        },
        {
            "id": "task1479-ade16d9699c54bbf9d2c3b16a0db9f09",
            "input": " NSA ? Rupert ? Tom Cruise ? A Goldman Sachs bankster ? Maybe some oil exploration execs on their way home from a junket http://t.co/FrR7CibegR",
            "output": [
                "Goldman Sachs"
            ]
        },
        {
            "id": "task1479-3fd3878bf33848059575ceddc9d66470",
            "input": " The Marx Brothers in Duck Superlative . #stylewars",
            "output": [
                "The Marx Brothers"
            ]
        },
        {
            "id": "task1479-6724445ce9494f42bd0728d9d0e0546a",
            "input": " Australia 's seat on UN Security Council was a big joke to conservatives . Remember that , Tony Abbott ? #MH17 #auspol http://t.co/pOAmuHVWCp",
            "output": [
                "UN Security Council"
            ]
        },
        {
            "id": "task1479-823819f30d2b4f8aa443bc3e9cb28f58",
            "input": " @ SeanFionn Labour 's way with the elder lemons from the Worker 's Party & their politburo mentality - do n't get me started on bullying ! ! ! !",
            "output": [
                "Worker 's Party"
            ]
        },
        {
            "id": "task1479-9420e67dcc3a4af683c820a54216ac22",
            "input": " Manchester City are a point away from the title . They 've been exhilarating , dynamic , entertaining and ruthless this season .",
            "output": [
                "Manchester City"
            ]
        },
        {
            "id": "task1479-7b7aef41c952454cb9b4c2d0a2d4ac6c",
            "input": " Buxton FC chairman says Scott Maxfield 's original appointment as Buxton boss had been an '\"' open-ended arrangement , to see how things went . '\"'",
            "output": [
                "Buxton FC"
            ]
        },
        {
            "id": "task1479-e3e0f622412c406e906819e1092d7855",
            "input": " middle aged man band playing blink 182 . l0 l .",
            "output": [
                "blink 182 ."
            ]
        },
        {
            "id": "task1479-380e372204a44cbb8cc9a46999324ca6",
            "input": " . @ KailashChandOBE GP practices run by SSP Healthcare in Sefton use locums . Patients describe lack of continuity and appointment delays .",
            "output": [
                "SSP Healthcare"
            ]
        },
        {
            "id": "task1479-9aad4d2e3831448880bb885248dfc75c",
            "input": " Same goes for the new Lamb of God stuff too !",
            "output": [
                "Lamb of God"
            ]
        },
        {
            "id": "task1479-8291004cfcf341b4a09265be2f785d04",
            "input": " What traffic looks like if you jump from a sleepy company in half stealth mode to # 1 on Hacker News #CDN #webperf https://t.co/zhLjzySIVV",
            "output": [
                "Hacker News"
            ]
        },
        {
            "id": "task1479-24c0c00ef00e47058d5b8605576481d0",
            "input": " Keynote customer Royal Philips shares its experiences on running mobile and web performance monitoring #webperf http://t.co/F1R9mrnstZ",
            "output": [
                "Royal Philips"
            ]
        },
        {
            "id": "task1479-53aa97a370184fbc8bd4ed1862e5282c",
            "input": " How Royal Philips runs mobile performance monitoring and how to get started http://t.co/R2Xayc9IdL #webperf",
            "output": [
                "Royal Philips"
            ]
        },
        {
            "id": "task1479-d4ce980fd539450e8bd2768e27931a89",
            "input": " @ andrewgdotcom @ alaninbelfast \" Cockup \" , is that the new NI 21 motto ",
            "output": [
                "?NI 21"
            ]
        },
        {
            "id": "task1479-d282e82c6b2b4b1b96c8e29ff97564d8",
            "input": " Prof @ bjsheehan7 comments on the the Publicis- Omnicom split http://t.co/1kTVmoZdDO",
            "output": [
                "Publicis- Omnicom"
            ]
        },
        {
            "id": "task1479-be232ebef88f43fdbd877d2324954378",
            "input": " Amazon 's Failed Pitch to Authors ( @ vauhinivara / New Yorker ) http://t.co/66IsxRknx4 http://t.co/H8TmqV3TPG",
            "output": [
                "New Yorker"
            ]
        },
        {
            "id": "task1479-e855786fbeb14b44b20a966b6225cf8b",
            "input": " Face your demons ! Salford City Council launch Stop Smoking Campaign http://t.co/M0KUGMLD",
            "output": [
                "Salford City Council"
            ]
        },
        {
            "id": "task1479-841cf6e8e41a4d4dac6539605782a434",
            "input": " Delon Armitage has been suspended from the England Saxons squad after being arrested and bailed on suspicion of assault . # rugbyunion",
            "output": [
                "England Saxons"
            ]
        },
        {
            "id": "task1479-feaadce4889145a5a3bde5eba6e830cf",
            "input": " MORE : KLM airlines to avoid #Ukraine crash site zone ' as precautionary measure ' http://t.co/W3FuCzbRwd #MH17 http://t.co/swZ5Te8xJ8",
            "output": [
                "KLM airlines"
            ]
        },
        {
            "id": "task1479-529e0c4256ea4d0daf1e087abed8cd47",
            "input": " Deeply moved by the warm welcome from the Victoria School and community in Villers- Bretonneux today http://t.co/SIFF7h6mqB",
            "output": [
                "Victoria School"
            ]
        },
        {
            "id": "task1479-91d6117f74ce49b09ae967ea6b25a0d8",
            "input": " Even Radio National is playing No Secrets and not to introduce a segment about FOI reform . RIP Doc Neeson",
            "output": [
                "Radio National"
            ]
        },
        {
            "id": "task1479-447f7a26787d4b329346464a440e1935",
            "input": " At the Eagleby Learning College Careers Day http://t.co/mf2I2OwSeX",
            "output": [
                "Eagleby Learning College"
            ]
        },
        {
            "id": "task1479-8db9e8bcf1fd41e3b5888a3524e8ff7e",
            "input": " Phunkation a funky / hardgroove techno label joins the Label Worx distribution family !",
            "output": [
                "Label Worx"
            ]
        },
        {
            "id": "task1479-bbc7611490524be0832a7b734e2bd645",
            "input": " In this week 's Commons debate on the civil service , I recounted my experience of the lifts in the Ministry of Justice http://t.co/UOc3qefpZ5",
            "output": [
                "Ministry of Justice"
            ]
        },
        {
            "id": "task1479-d96c4e849c3642cf9336153ec185d6fe",
            "input": " CNN International credits user generated video content 53 % of the time , more often than any other outlethttp : / / nie.mn/1kESdTY",
            "output": [
                "CNN International"
            ]
        },
        {
            "id": "task1479-99b817bbf29243718ec432d2ca7984dc",
            "input": " The Ecco Shoes UK Daily is out ! http://t.co/uIvExTtR ▸ Top stories today via nomik33 laroyal06 ecco_uk jbgwbkntbya lovethoseshoes",
            "output": [
                "Ecco Shoes"
            ]
        },
        {
            "id": "task1479-cda80fe74dd048a8a1d3df334b7b0333",
            "input": " #ghana Portugal - a Single Game Suspension for Pepe : http://t.co/qJYTkMuNfZ",
            "output": [
                "#ghana Portugal"
            ]
        },
        {
            "id": "task1479-e551232314634f3283dd590c966d7883",
            "input": " Sesión preparatoria antes del #RSORealMadrid. #halamadrid http://t.co/frEUVKJ4OS",
            "output": [
                "#RSORealMadrid. #halamadrid"
            ]
        },
        {
            "id": "task1479-da4adc98f41e4362955b0ce73bcc9824",
            "input": " Journalism majors visit the Associated Press this morning where they sat in on the world-wide morning meeting . http://t.co/PDMBbECpbD",
            "output": [
                "Associated Press"
            ]
        },
        {
            "id": "task1479-90ec0a4f7d044a6ebfb181a64505a8a1",
            "input": " Written Answers- Employment : Cannock Chase ( 16 June 2014 ) Aidan Burley : To ask the Minister for the Cabinet Office . . http://t.co/jlvvb5YHge",
            "output": [
                "Cabinet Office"
            ]
        },
        {
            "id": "task1479-4c1fc86e1d1e441e80e33bb968325800",
            "input": " I 'd urge Bryan to fight hard but that goes without saying for a member of the Murray clan of Shawville , Que .",
            "output": [
                "Murray clan"
            ]
        },
        {
            "id": "task1479-62aa3d83a7cb47c0b681c78d36968227",
            "input": " In today 's Irish News : GAA Fixtures in Irish News #everyfixture #everytuesday #everyclub #everyball #everysliotar",
            "output": [
                "Irish News"
            ]
        },
        {
            "id": "task1479-23a19be2dccb487c863838a0d2898828",
            "input": " In tmro 's Irish News : Mickey bashers , referee criticism and Antrim club fixtures - get it off your chest in Off The Fence #gaa",
            "output": [
                "Irish News"
            ]
        },
        {
            "id": "task1479-704bde789c3c40279001d078b403d488",
            "input": " In today 's Irish News : sponsored walks , match tickets and golf classics - all the news from the parish in CLUBcall #EveryClub",
            "output": [
                "Irish News"
            ]
        },
        {
            "id": "task1479-af0566638d1f41cd8c9bcfab038dd637",
            "input": " In the Irish News tmro : Monaghan ladies reached yet another Provincial decider by easily overcoming senior championship debutants , Cavan .",
            "output": [
                "Irish News"
            ]
        },
        {
            "id": "task1479-259a320127cc45ffaa41454384e97ef3",
            "input": " In Irish News tmro : Injuries have forced @ Doiregaa into changes ahead of Saturday ’ s All- Ireland SFC Qualifier Round 1 clash #EveryBall",
            "output": [
                "Irish News"
            ]
        },
        {
            "id": "task1479-3f12be1722a2436d8bcbe2c02e4bdac2",
            "input": " In today 's Irish News : Sunday ’ s crowd at Clones will get value for their money from Antrim says Saffrons manager Liam Bradley #EveryBall",
            "output": [
                "Irish News"
            ]
        },
        {
            "id": "task1479-86252519b0b84363b6c6293fa80d6322",
            "input": " In today 's Irish News : WIN @ Armagh_GAA v @monaghangaa Ulster Championship tickets @ UlsterGAA - # 5 pairs to be won #Ulster2014",
            "output": [
                "Irish News"
            ]
        },
        {
            "id": "task1479-c16814ee17504f10ad7a65d5060c2914",
            "input": " In tmro 's Irish News : Rory has made his Olympic choice , but he 'll have to be on top of his game to win the @IrishOpen2014 we look ahead",
            "output": [
                "Irish News"
            ]
        },
        {
            "id": "task1479-4680443e84474294869ef489d1288e27",
            "input": " Ferrari World ( the calm ) before we tore up the track . Aston Martin coup . #abudhabi @ mrodofficial http://t.co/BjOos2Jb1M",
            "output": [
                "Aston Martin"
            ]
        },
        {
            "id": "task1479-7673f1778ef34c1e9c95d5f2bb48c284",
            "input": " Meanwhile #Moscow residents write ' Excuse us ' at the Dutch embassy in #Russia #MH17 #Ukraine http://t.co/I7qzRIVF3F",
            "output": [
                "Dutch embassy"
            ]
        },
        {
            "id": "task1479-a85846792f204bf2971e33499c55f905",
            "input": " Meanwhile #Moscow residents write ' Excuse us ' at the Dutch embassy in #Russia #MH17 http://t.co/HoMsaz5D2I \" @ MoscowTimes @ EvaHartog",
            "output": [
                "Dutch embassy"
            ]
        },
        {
            "id": "task1479-ea31c81573fc4b48bb3278b758089340",
            "input": " En media hora comienza el sorteo que dará con los rivales del Real Madrid en la Fase de Grupos de la #UCL. #UCLdraw #halamadrid",
            "output": [
                "Real Madrid"
            ]
        },
        {
            "id": "task1479-6d29a66c127341eaa822816bffe5724d",
            "input": " Proud to count so many Newspaper Guild #journalists among the winners and finalists of today 's #Pulitzers. http://t.co/9Gd21FV6Cn",
            "output": [
                "Newspaper Guild"
            ]
        },
        {
            "id": "task1479-6eeed275da6844999fde008c0fd81a8a",
            "input": " Arriving early to Dublin #BISA2014? Visit @ ucdpolitics with Irish FM speaking on ' Constitutions and Culture Wars ' http://t.co/us0EEQvyHB",
            "output": [
                "Irish FM"
            ]
        },
        {
            "id": "task1479-143fc741157a48c7bc596ee6c0fc8bc1",
            "input": " @ LukeyVivienne @ hammersmithandy Go , Labour team Hammersmith . It could n't be more important for you to win , for homes and the hospital .",
            "output": [
                "Labour team Hammersmith"
            ]
        },
        {
            "id": "task1479-da73f35e20c24bb58ef59f0a2b6d5ac2",
            "input": " Hector Bellerin starts for #AFC against Borussia Dortmund , according to team-mate http://t.co/XSDV47rAmm http://t.co/bHNpuBdOu6",
            "output": [
                "Borussia Dortmund"
            ]
        },
        {
            "id": "task1479-def5654ca4674735bfd240c7945375e0",
            "input": " \" We 're very appreciative ofthe Malaysian government 's position that is neutral & not blaming anyone . \" Russia envoy #MH17 http://t.co/0NaCAKQ5C6",
            "output": [
                "Malaysian government"
            ]
        },
        {
            "id": "task1479-d8059fb4e54447ebae3512a20ea956e0",
            "input": " Well-hung ? Palmer United Party senator Jacqui Lambie boards the Oversharing Express on radio station Heart 107 . 3 http://t.co/TiNBRmQndV",
            "output": [
                "Palmer United Party"
            ]
        },
        {
            "id": "task1479-590b5b1aae1e47c293f0c0575c4ea5b8",
            "input": " . @ joseiswriting , America ’ s most famous unauthorized immigrant , detained by Border Patrol http://t.co/nIlmMacWO8",
            "output": [
                "Border Patrol"
            ]
        },
        {
            "id": "task1479-01d5a05444394508bba7d299518b7d9a",
            "input": " Looking forward to commemorating Khalsa Hockey Club 's 40th anniversary at their annual awards dinner this eve",
            "output": [
                "Khalsa Hockey Club"
            ]
        },
        {
            "id": "task1479-93251ad5c92d44b0859f49977e8db20c",
            "input": " So what does the weekend hold ? Liverpool v Man Utd for me tomorrow . Not expecting a quiet one . FA Cup weekend still got the old magic .",
            "output": [
                "Man Utd"
            ]
        },
        {
            "id": "task1479-050eaa9f53254c2cac1ab5ec848b740c",
            "input": " Anti-aircraft weapon \" Buk \" in Snizhne , Donetsk region today . #MH17 #boeing777 #MalaysiaAirlines http://t.co/FVym2Syw0s",
            "output": [
                "#boeing777 #MalaysiaAirlines"
            ]
        },
        {
            "id": "task1479-ac2486c72499444d921da7d38cf22c5f",
            "input": " Right now Russian media have started campaign to accuse Ukrainian military for #MH17 #flightmh17 crash . Nobody trusts Russia now !",
            "output": [
                "Ukrainian military"
            ]
        },
        {
            "id": "task1479-85e8959da75a445d9d68bc309bd21163",
            "input": " Check out J Whaley Music upcoming show . Dope singer doing his thing out in #Nashville http://t.co/fIAXaBrn04",
            "output": [
                "J Whaley Music"
            ]
        },
        {
            "id": "task1479-7f5eb9a0ff2240a7a99844b8b0d2b563",
            "input": " Best comment : from bemused Lib Dem activist \" I went to bed with 12 MEPs and woke up with 1 \"",
            "output": [
                "Lib Dem"
            ]
        },
        {
            "id": "task1479-e27d8b287caf4557bc6a9e11fc4324c9",
            "input": " Nice #airgait goal by @ CurtisDickson17 CAN leads Iroquois Nation 8 - 3 in 3rd quarter of World Field Lax game . Currently on TSN 2 .",
            "output": [
                "Iroquois Nation"
            ]
        },
        {
            "id": "task1479-4a3522adf7b44a5e9a77337e9752eb04",
            "input": " @ bbc606 @ PSV gotta be a win for the home franchise on the afternoon but can see the French guys troubling the Blue Lions deefense .",
            "output": [
                "Blue Lions"
            ]
        },
        {
            "id": "task1479-15522838b0e3457aa7ea810a4a7accb4",
            "input": " In Parliament today in the return of the first sitting week , I tabled two reports of the Public Works Committee . . . . http://t.co/GHsJ2oG3bJ",
            "output": [
                "Public Works Committee"
            ]
        },
        {
            "id": "task1479-82901afbb93a48ada1bbcf0924607e87",
            "input": " Landslide victory for Sinn Féin : the 1918 general election : http://t.co/96TkhnBUfo",
            "output": [
                "Sinn Féin"
            ]
        },
        {
            "id": "task1479-b149388ea814445c9addf68328eb81da",
            "input": " Latest : Daithí McKay : Sinn Féin will not be deflected by ' old guard ' within the police http://t.co/qZmErJoyOS",
            "output": [
                "Sinn Féin"
            ]
        },
        {
            "id": "task1479-2ea8a864b9024fceadda8f4d439c939d",
            "input": " fabulous locally produced food for sale at Kate Humble 's Humble by Nature shop and cafe @ farmerhumble http://t.co/bZWusofKVw",
            "output": [
                "Humble by Nature"
            ]
        },
        {
            "id": "task1479-31a693051a234afa89881a544d07fb35",
            "input": " MT @ hdevreij : Airliners now taking evasive action to avoid e . #Ukraine airspace . Ex . : Flight TG 921 Thai Airways http://t.co/CttSAnHCh4 #MH17",
            "output": [
                "Thai Airways"
            ]
        },
        {
            "id": "task1479-d9d94947c2a347faabf746396a884e49",
            "input": " Parliamentary Library ’ s latest blog brings balance to : GP co-payments , PPL , direct action , and pension indexation . http://t.co/T1qxqP0jwf",
            "output": [
                "Parliamentary Library"
            ]
        },
        {
            "id": "task1479-28839f6eaf8b4e2fb937efecf6937922",
            "input": " Why when I pay Virgin Media for 50 mb broadband , is it faster when I use 3 G on my phone ",
            "output": [
                "?Virgin Media"
            ]
        }
    ],
    "Instance License": [
        "CC BY 4.0"
    ]
}